<?xml version="1.0"?>
<Results version="1.0">
<ReportNode type="testrun">
<ReportNode type="Iteration">
<ReportNode type="Action">
<ReportNode type="Iteration">
<ReportNode type="Step">
<Data>
    <Name>LoadFunctionLibrary</Name>
    <Description>LoadFunctionLibrary function passed</Description>
    <StartTime>2023-06-05 14:07:48</StartTime>
    <Result>Passed</Result>
    <Extension>
      <IconKey>6b3571f267314fd8800e5e9f08d7df52</IconKey>
      <IsPlainTextNodeName>True</IsPlainTextNodeName>
    </Extension>
    <DeviceInfo />
  </Data>
</ReportNode>
<ReportNode type="Step">
<Data>
    <Name>LoadFunctionLibrary</Name>
    <Description>LoadFunctionLibrary function passed</Description>
    <StartTime>2023-06-05 14:07:48</StartTime>
    <Result>Passed</Result>
    <Extension>
      <IconKey>6b3571f267314fd8800e5e9f08d7df52</IconKey>
      <IsPlainTextNodeName>True</IsPlainTextNodeName>
    </Extension>
    <DeviceInfo />
  </Data>
</ReportNode>
<ReportNode type="Step">
<Data>
    <Name>LoadFunctionLibrary</Name>
    <Description>LoadFunctionLibrary function passed</Description>
    <StartTime>2023-06-05 14:07:48</StartTime>
    <Result>Passed</Result>
    <Extension>
      <IconKey>6b3571f267314fd8800e5e9f08d7df52</IconKey>
      <IsPlainTextNodeName>True</IsPlainTextNodeName>
    </Extension>
    <DeviceInfo />
  </Data>
</ReportNode>
<ReportNode type="Step">
<Data>
    <Name>LoadFunctionLibrary</Name>
    <Description>LoadFunctionLibrary function passed</Description>
    <StartTime>2023-06-05 14:07:48</StartTime>
    <Result>Passed</Result>
    <Extension>
      <IconKey>6b3571f267314fd8800e5e9f08d7df52</IconKey>
      <IsPlainTextNodeName>True</IsPlainTextNodeName>
    </Extension>
    <DeviceInfo />
  </Data>
</ReportNode>
<ReportNode type="Step">
<Data>
    <Name>LoadFunctionLibrary</Name>
    <Description>LoadFunctionLibrary function passed</Description>
    <StartTime>2023-06-05 14:07:48</StartTime>
    <Result>Passed</Result>
    <Extension>
      <IconKey>6b3571f267314fd8800e5e9f08d7df52</IconKey>
      <IsPlainTextNodeName>True</IsPlainTextNodeName>
    </Extension>
    <DeviceInfo />
  </Data>
</ReportNode>
<ReportNode type="Context">
<ReportNode type="Step">
<Data>
    <Name>Ok_Kerahasiaan.Exist</Name>
    <Description>"Object does not exist"</Description>
    <StartTime>2023-06-05 14:08:02</StartTime>
    <Result>Done</Result>
    <Extension>
      <TestObject>
        <Repository>D:\BNI All\Mobile Keagenan Android\Lib_Repo_Excel_Keagenan_Mobile\Repo_Keagenan_Mobile\RP_Keagenan_Mobile.tsr</Repository>
        <Path>
          <Object>
            <Type>Device</Type>
            <Name><![CDATA[Device]]></Name>
          </Object>
          <Object>
            <Type>InsightObject</Type>
            <Name><![CDATA[Ok_Kerahasiaan]]></Name>
          </Object>
        </Path>
        <Operation>Exist</Operation>
        <OperationData><![CDATA["Object does not exist"]]></OperationData>
      </TestObject>
      <IconKey>edebde20480244f29877c7f0b014bf4b</IconKey>
      <IsPlainTextNodeName>True</IsPlainTextNodeName>
    </Extension>
    <DeviceInfo />
  </Data>
</ReportNode>
<ReportNode type="Step">
<Data>
    <Name>Username.Exist</Name>
    <Description>"Object does not exist"</Description>
    <StartTime>2023-06-05 14:08:05</StartTime>
    <Result>Done</Result>
    <Extension>
      <TestObject>
        <Repository>D:\BNI All\Mobile Keagenan Android\Lib_Repo_Excel_Keagenan_Mobile\Repo_Keagenan_Mobile\RP_KeagenanMobile_Login.tsr</Repository>
        <Path>
          <Object>
            <Type>Device</Type>
            <Name><![CDATA[Device]]></Name>
          </Object>
          <Object>
            <Type>InsightObject</Type>
            <Name><![CDATA[Username]]></Name>
          </Object>
        </Path>
        <Operation>Exist</Operation>
        <OperationData><![CDATA["Object does not exist"]]></OperationData>
      </TestObject>
      <IconKey>edebde20480244f29877c7f0b014bf4b</IconKey>
      <IsPlainTextNodeName>True</IsPlainTextNodeName>
    </Extension>
    <DeviceInfo />
  </Data>
</ReportNode>
<ReportNode type="Step">
<Data>
    <Name>Ok_Kerahasiaan.Exist</Name>
    <Description>"Object does not exist"</Description>
    <StartTime>2023-06-05 14:08:05</StartTime>
    <Result>Done</Result>
    <Extension>
      <TestObject>
        <Repository>D:\BNI All\Mobile Keagenan Android\Lib_Repo_Excel_Keagenan_Mobile\Repo_Keagenan_Mobile\RP_Keagenan_Mobile.tsr</Repository>
        <Path>
          <Object>
            <Type>Device</Type>
            <Name><![CDATA[Device]]></Name>
          </Object>
          <Object>
            <Type>InsightObject</Type>
            <Name><![CDATA[Ok_Kerahasiaan]]></Name>
          </Object>
        </Path>
        <Operation>Exist</Operation>
        <OperationData><![CDATA["Object does not exist"]]></OperationData>
      </TestObject>
      <IconKey>edebde20480244f29877c7f0b014bf4b</IconKey>
      <IsPlainTextNodeName>True</IsPlainTextNodeName>
    </Extension>
    <DeviceInfo />
  </Data>
</ReportNode>
<ReportNode type="Step">
<Data>
    <Name>Username.Exist</Name>
    <Description>"Object does not exist"</Description>
    <StartTime>2023-06-05 14:08:08</StartTime>
    <Result>Done</Result>
    <Extension>
      <TestObject>
        <Repository>D:\BNI All\Mobile Keagenan Android\Lib_Repo_Excel_Keagenan_Mobile\Repo_Keagenan_Mobile\RP_KeagenanMobile_Login.tsr</Repository>
        <Path>
          <Object>
            <Type>Device</Type>
            <Name><![CDATA[Device]]></Name>
          </Object>
          <Object>
            <Type>InsightObject</Type>
            <Name><![CDATA[Username]]></Name>
          </Object>
        </Path>
        <Operation>Exist</Operation>
        <OperationData><![CDATA["Object does not exist"]]></OperationData>
      </TestObject>
      <IconKey>edebde20480244f29877c7f0b014bf4b</IconKey>
      <IsPlainTextNodeName>True</IsPlainTextNodeName>
    </Extension>
    <DeviceInfo />
  </Data>
</ReportNode>
<ReportNode type="Step">
<Data>
    <Name>Ok_Kerahasiaan.Exist</Name>
    <Description>"Object does not exist"</Description>
    <StartTime>2023-06-05 14:08:08</StartTime>
    <Result>Done</Result>
    <Extension>
      <TestObject>
        <Repository>D:\BNI All\Mobile Keagenan Android\Lib_Repo_Excel_Keagenan_Mobile\Repo_Keagenan_Mobile\RP_Keagenan_Mobile.tsr</Repository>
        <Path>
          <Object>
            <Type>Device</Type>
            <Name><![CDATA[Device]]></Name>
          </Object>
          <Object>
            <Type>InsightObject</Type>
            <Name><![CDATA[Ok_Kerahasiaan]]></Name>
          </Object>
        </Path>
        <Operation>Exist</Operation>
        <OperationData><![CDATA["Object does not exist"]]></OperationData>
      </TestObject>
      <IconKey>edebde20480244f29877c7f0b014bf4b</IconKey>
      <IsPlainTextNodeName>True</IsPlainTextNodeName>
    </Extension>
    <DeviceInfo />
  </Data>
</ReportNode>
<ReportNode type="Step">
<Data>
    <Name>Username.Exist</Name>
    <Description>"Object does not exist"</Description>
    <StartTime>2023-06-05 14:08:11</StartTime>
    <Result>Done</Result>
    <Extension>
      <TestObject>
        <Repository>D:\BNI All\Mobile Keagenan Android\Lib_Repo_Excel_Keagenan_Mobile\Repo_Keagenan_Mobile\RP_KeagenanMobile_Login.tsr</Repository>
        <Path>
          <Object>
            <Type>Device</Type>
            <Name><![CDATA[Device]]></Name>
          </Object>
          <Object>
            <Type>InsightObject</Type>
            <Name><![CDATA[Username]]></Name>
          </Object>
        </Path>
        <Operation>Exist</Operation>
        <OperationData><![CDATA["Object does not exist"]]></OperationData>
      </TestObject>
      <IconKey>edebde20480244f29877c7f0b014bf4b</IconKey>
      <IsPlainTextNodeName>True</IsPlainTextNodeName>
    </Extension>
    <DeviceInfo />
  </Data>
</ReportNode>
<ReportNode type="Step">
<Data>
    <Name>Ok_Kerahasiaan.Exist</Name>
    <Description>"Object exists"</Description>
    <StartTime>2023-06-05 14:08:11</StartTime>
    <Result>Done</Result>
    <Extension>
      <TestObject>
        <Repository>D:\BNI All\Mobile Keagenan Android\Lib_Repo_Excel_Keagenan_Mobile\Repo_Keagenan_Mobile\RP_Keagenan_Mobile.tsr</Repository>
        <Path>
          <Object>
            <Type>Device</Type>
            <Name><![CDATA[Device]]></Name>
          </Object>
          <Object>
            <Type>InsightObject</Type>
            <Name><![CDATA[Ok_Kerahasiaan]]></Name>
          </Object>
        </Path>
        <Operation>Exist</Operation>
        <OperationData><![CDATA["Object exists"]]></OperationData>
      </TestObject>
      <IconKey>edebde20480244f29877c7f0b014bf4b</IconKey>
      <IsPlainTextNodeName>True</IsPlainTextNodeName>
    </Extension>
    <DeviceInfo />
  </Data>
</ReportNode>
<ReportNode type="Step">
<Data>
    <Name>Ok_Kerahasiaan.Click</Name>
    <Description />
    <StartTime>2023-06-05 14:08:12</StartTime>
    <Result>Done</Result>
    <Extension>
      <TestObject>
        <Repository>D:\BNI All\Mobile Keagenan Android\Lib_Repo_Excel_Keagenan_Mobile\Repo_Keagenan_Mobile\RP_Keagenan_Mobile.tsr</Repository>
        <Path>
          <Object>
            <Type>Device</Type>
            <Name><![CDATA[Device]]></Name>
          </Object>
          <Object>
            <Type>InsightObject</Type>
            <Name><![CDATA[Ok_Kerahasiaan]]></Name>
          </Object>
        </Path>
        <Operation>Click</Operation>
      </TestObject>
      <IconKey>edebde20480244f29877c7f0b014bf4b</IconKey>
      <IsPlainTextNodeName>True</IsPlainTextNodeName>
    </Extension>
    <DeviceInfo />
  </Data>
</ReportNode>
<ReportNode type="Step">
<Data>
    <Name>Username.Exist</Name>
    <Description>"Object does not exist"</Description>
    <StartTime>2023-06-05 14:08:12</StartTime>
    <Result>Done</Result>
    <Extension>
      <TestObject>
        <Repository>D:\BNI All\Mobile Keagenan Android\Lib_Repo_Excel_Keagenan_Mobile\Repo_Keagenan_Mobile\RP_KeagenanMobile_Login.tsr</Repository>
        <Path>
          <Object>
            <Type>Device</Type>
            <Name><![CDATA[Device]]></Name>
          </Object>
          <Object>
            <Type>InsightObject</Type>
            <Name><![CDATA[Username]]></Name>
          </Object>
        </Path>
        <Operation>Exist</Operation>
        <OperationData><![CDATA["Object does not exist"]]></OperationData>
      </TestObject>
      <IconKey>edebde20480244f29877c7f0b014bf4b</IconKey>
      <IsPlainTextNodeName>True</IsPlainTextNodeName>
    </Extension>
    <DeviceInfo />
  </Data>
</ReportNode>
<ReportNode type="Step">
<Data>
    <Name>Ok_Kerahasiaan.Exist</Name>
    <Description>"Object exists"</Description>
    <StartTime>2023-06-05 14:08:12</StartTime>
    <Result>Done</Result>
    <Extension>
      <TestObject>
        <Repository>D:\BNI All\Mobile Keagenan Android\Lib_Repo_Excel_Keagenan_Mobile\Repo_Keagenan_Mobile\RP_Keagenan_Mobile.tsr</Repository>
        <Path>
          <Object>
            <Type>Device</Type>
            <Name><![CDATA[Device]]></Name>
          </Object>
          <Object>
            <Type>InsightObject</Type>
            <Name><![CDATA[Ok_Kerahasiaan]]></Name>
          </Object>
        </Path>
        <Operation>Exist</Operation>
        <OperationData><![CDATA["Object exists"]]></OperationData>
      </TestObject>
      <IconKey>edebde20480244f29877c7f0b014bf4b</IconKey>
      <IsPlainTextNodeName>True</IsPlainTextNodeName>
    </Extension>
    <DeviceInfo />
  </Data>
</ReportNode>
<ReportNode type="Step">
<Data>
    <Name>Ok_Kerahasiaan.Click</Name>
    <Description />
    <StartTime>2023-06-05 14:08:13</StartTime>
    <Result>Done</Result>
    <Extension>
      <TestObject>
        <Repository>D:\BNI All\Mobile Keagenan Android\Lib_Repo_Excel_Keagenan_Mobile\Repo_Keagenan_Mobile\RP_Keagenan_Mobile.tsr</Repository>
        <Path>
          <Object>
            <Type>Device</Type>
            <Name><![CDATA[Device]]></Name>
          </Object>
          <Object>
            <Type>InsightObject</Type>
            <Name><![CDATA[Ok_Kerahasiaan]]></Name>
          </Object>
        </Path>
        <Operation>Click</Operation>
      </TestObject>
      <IconKey>edebde20480244f29877c7f0b014bf4b</IconKey>
      <IsPlainTextNodeName>True</IsPlainTextNodeName>
    </Extension>
    <DeviceInfo />
  </Data>
</ReportNode>
<ReportNode type="Step">
<Data>
    <Name>Username.Exist</Name>
    <Description>"Object exists"</Description>
    <StartTime>2023-06-05 14:08:13</StartTime>
    <Result>Done</Result>
    <Extension>
      <TestObject>
        <Repository>D:\BNI All\Mobile Keagenan Android\Lib_Repo_Excel_Keagenan_Mobile\Repo_Keagenan_Mobile\RP_KeagenanMobile_Login.tsr</Repository>
        <Path>
          <Object>
            <Type>Device</Type>
            <Name><![CDATA[Device]]></Name>
          </Object>
          <Object>
            <Type>InsightObject</Type>
            <Name><![CDATA[Username]]></Name>
          </Object>
        </Path>
        <Operation>Exist</Operation>
        <OperationData><![CDATA["Object exists"]]></OperationData>
      </TestObject>
      <IconKey>edebde20480244f29877c7f0b014bf4b</IconKey>
      <IsPlainTextNodeName>True</IsPlainTextNodeName>
    </Extension>
    <DeviceInfo />
  </Data>
</ReportNode>
<ReportNode type="Step">
<Data>
    <Name>Username.Exist</Name>
    <Description>"Object exists"</Description>
    <StartTime>2023-06-05 14:08:25</StartTime>
    <Result>Done</Result>
    <Extension>
      <TestObject>
        <Repository>D:\BNI All\Mobile Keagenan Android\Lib_Repo_Excel_Keagenan_Mobile\Repo_Keagenan_Mobile\RP_KeagenanMobile_Login.tsr</Repository>
        <Path>
          <Object>
            <Type>Device</Type>
            <Name><![CDATA[Device]]></Name>
          </Object>
          <Object>
            <Type>InsightObject</Type>
            <Name><![CDATA[Username]]></Name>
          </Object>
        </Path>
        <Operation>Exist</Operation>
        <OperationData><![CDATA["Object exists"]]></OperationData>
      </TestObject>
      <IconKey>edebde20480244f29877c7f0b014bf4b</IconKey>
      <IsPlainTextNodeName>True</IsPlainTextNodeName>
    </Extension>
    <DeviceInfo />
  </Data>
</ReportNode>
<ReportNode type="Step">
<Data>
    <Name>Username.Click</Name>
    <Description />
    <StartTime>2023-06-05 14:08:25</StartTime>
    <Result>Done</Result>
    <Extension>
      <TestObject>
        <Repository>D:\BNI All\Mobile Keagenan Android\Lib_Repo_Excel_Keagenan_Mobile\Repo_Keagenan_Mobile\RP_KeagenanMobile_Login.tsr</Repository>
        <Path>
          <Object>
            <Type>Device</Type>
            <Name><![CDATA[Device]]></Name>
          </Object>
          <Object>
            <Type>InsightObject</Type>
            <Name><![CDATA[Username]]></Name>
          </Object>
        </Path>
        <Operation>Click</Operation>
      </TestObject>
      <IconKey>edebde20480244f29877c7f0b014bf4b</IconKey>
      <IsPlainTextNodeName>True</IsPlainTextNodeName>
    </Extension>
    <DeviceInfo />
  </Data>
</ReportNode>
<ReportNode type="Step">
<Data>
    <Name>Password_Login.Exist</Name>
    <Description>"Object exists"</Description>
    <StartTime>2023-06-05 14:08:31</StartTime>
    <Result>Done</Result>
    <Extension>
      <TestObject>
        <Repository>D:\BNI All\Mobile Keagenan Android\Lib_Repo_Excel_Keagenan_Mobile\Repo_Keagenan_Mobile\RP_KeagenanMobile_Login.tsr</Repository>
        <Path>
          <Object>
            <Type>Device</Type>
            <Name><![CDATA[Device]]></Name>
          </Object>
          <Object>
            <Type>InsightObject</Type>
            <Name><![CDATA[Password_Login]]></Name>
          </Object>
        </Path>
        <Operation>Exist</Operation>
        <OperationData><![CDATA["Object exists"]]></OperationData>
      </TestObject>
      <IconKey>edebde20480244f29877c7f0b014bf4b</IconKey>
      <IsPlainTextNodeName>True</IsPlainTextNodeName>
    </Extension>
    <DeviceInfo />
  </Data>
</ReportNode>
<ReportNode type="Step">
<Data>
    <Name>Password_Login.Click</Name>
    <Description />
    <StartTime>2023-06-05 14:08:32</StartTime>
    <Result>Done</Result>
    <Extension>
      <TestObject>
        <Repository>D:\BNI All\Mobile Keagenan Android\Lib_Repo_Excel_Keagenan_Mobile\Repo_Keagenan_Mobile\RP_KeagenanMobile_Login.tsr</Repository>
        <Path>
          <Object>
            <Type>Device</Type>
            <Name><![CDATA[Device]]></Name>
          </Object>
          <Object>
            <Type>InsightObject</Type>
            <Name><![CDATA[Password_Login]]></Name>
          </Object>
        </Path>
        <Operation>Click</Operation>
      </TestObject>
      <IconKey>edebde20480244f29877c7f0b014bf4b</IconKey>
      <IsPlainTextNodeName>True</IsPlainTextNodeName>
    </Extension>
    <DeviceInfo />
  </Data>
</ReportNode>
<ReportNode type="Step">
<Data>
    <Name>Masuk_Btn.Click</Name>
    <Description />
    <StartTime>2023-06-05 14:08:47</StartTime>
    <Result>Done</Result>
    <Extension>
      <TestObject>
        <Repository>D:\BNI All\Mobile Keagenan Android\Lib_Repo_Excel_Keagenan_Mobile\Repo_Keagenan_Mobile\RP_KeagenanMobile_Login.tsr</Repository>
        <Path>
          <Object>
            <Type>Device</Type>
            <Name><![CDATA[Device]]></Name>
          </Object>
          <Object>
            <Type>InsightObject</Type>
            <Name><![CDATA[Masuk_Btn]]></Name>
          </Object>
        </Path>
        <Operation>Click</Operation>
      </TestObject>
      <IconKey>edebde20480244f29877c7f0b014bf4b</IconKey>
      <IsPlainTextNodeName>True</IsPlainTextNodeName>
    </Extension>
    <DeviceInfo />
  </Data>
</ReportNode>
<ReportNode type="Context">
<ReportNode type="Step">
<Data>
    <Name>Akun.Tap</Name>
    <Description />
    <StartTime>2023-06-05 14:09:29</StartTime>
    <Result>Done</Result>
    <Extension>
      <TestObject>
        <Repository>D:\BNI All\Mobile Keagenan Android\Lib_Repo_Excel_Keagenan_Mobile\Repo_Keagenan_Mobile\RP_KeagenanMobile_RiwayatPesan.tsr</Repository>
        <Path>
          <Object>
            <Type>Device</Type>
            <Name><![CDATA[Device]]></Name>
          </Object>
          <Object>
            <Type>App</Type>
            <Name><![CDATA[BNI Agen46]]></Name>
          </Object>
          <Object>
            <Type>MobileObject</Type>
            <Name><![CDATA[Akun]]></Name>
          </Object>
        </Path>
        <Operation>Tap</Operation>
        <Properties>
          <Property>
            <Name><![CDATA[resourceid]]></Name>
            <Value><![CDATA[]]></Value>
          </Property>
          <Property>
            <Name><![CDATA[nativeclass]]></Name>
            <Value><![CDATA[android.view.View]]></Value>
          </Property>
          <Property>
            <Name><![CDATA[mcindex]]></Name>
            <Value><![CDATA[26]]></Value>
          </Property>
          <Property>
            <Name><![CDATA[class]]></Name>
            <Value><![CDATA[View]]></Value>
          </Property>
          <Property>
            <Name><![CDATA[accessibilityid]]></Name>
            <Value><![CDATA[Akun]]></Value>
          </Property>
        </Properties>
      </TestObject>
      <IconKey>2942059282e44749a06ac7e476c1b694</IconKey>
      <IsPlainTextNodeName>True</IsPlainTextNodeName>
    </Extension>
    <DeviceInfo />
  </Data>
</ReportNode>
<ReportNode type="Step">
<Data>
    <Name>Riwayat Pesan.Tap</Name>
    <Description />
    <StartTime>2023-06-05 14:09:45</StartTime>
    <Result>Done</Result>
    <Extension>
      <TestObject>
        <Repository>D:\BNI All\Mobile Keagenan Android\Lib_Repo_Excel_Keagenan_Mobile\Repo_Keagenan_Mobile\RP_KeagenanMobile_RiwayatPesan.tsr</Repository>
        <Path>
          <Object>
            <Type>Device</Type>
            <Name><![CDATA[Device]]></Name>
          </Object>
          <Object>
            <Type>App</Type>
            <Name><![CDATA[BNI Agen46]]></Name>
          </Object>
          <Object>
            <Type>MobileObject</Type>
            <Name><![CDATA[Riwayat Pesan]]></Name>
          </Object>
        </Path>
        <Operation>Tap</Operation>
        <Properties>
          <Property>
            <Name><![CDATA[resourceid]]></Name>
            <Value><![CDATA[]]></Value>
          </Property>
          <Property>
            <Name><![CDATA[nativeclass]]></Name>
            <Value><![CDATA[android.widget.ImageView]]></Value>
          </Property>
          <Property>
            <Name><![CDATA[mcindex]]></Name>
            <Value><![CDATA[6]]></Value>
          </Property>
          <Property>
            <Name><![CDATA[class]]></Name>
            <Value><![CDATA[ImageView]]></Value>
          </Property>
          <Property>
            <Name><![CDATA[accessibilityid]]></Name>
            <Value><![CDATA[Riwayat Pesan]]></Value>
          </Property>
        </Properties>
      </TestObject>
      <IconKey>2942059282e44749a06ac7e476c1b694</IconKey>
      <IsPlainTextNodeName>True</IsPlainTextNodeName>
    </Extension>
    <DeviceInfo />
  </Data>
</ReportNode>
<ReportNode type="Step">
<Data>
    <Name>Belum Terbaca.Tap</Name>
    <Description />
    <StartTime>2023-06-05 14:10:00</StartTime>
    <Result>Done</Result>
    <Extension>
      <TestObject>
        <Repository>D:\BNI All\Mobile Keagenan Android\Lib_Repo_Excel_Keagenan_Mobile\Repo_Keagenan_Mobile\RP_KeagenanMobile_RiwayatPesan.tsr</Repository>
        <Path>
          <Object>
            <Type>Device</Type>
            <Name><![CDATA[Device]]></Name>
          </Object>
          <Object>
            <Type>App</Type>
            <Name><![CDATA[BNI Agen46]]></Name>
          </Object>
          <Object>
            <Type>MobileObject</Type>
            <Name><![CDATA[Belum Terbaca]]></Name>
          </Object>
        </Path>
        <Operation>Tap</Operation>
        <Properties>
          <Property>
            <Name><![CDATA[resourceid]]></Name>
            <Value><![CDATA[]]></Value>
          </Property>
          <Property>
            <Name><![CDATA[nativeclass]]></Name>
            <Value><![CDATA[android.view.View]]></Value>
          </Property>
          <Property>
            <Name><![CDATA[mcindex]]></Name>
            <Value><![CDATA[12]]></Value>
          </Property>
          <Property>
            <Name><![CDATA[class]]></Name>
            <Value><![CDATA[View]]></Value>
          </Property>
          <Property>
            <Name><![CDATA[accessibilityid]]></Name>
            <Value><![CDATA[Belum Terbaca]]></Value>
          </Property>
        </Properties>
      </TestObject>
      <IconKey>2942059282e44749a06ac7e476c1b694</IconKey>
      <IsPlainTextNodeName>True</IsPlainTextNodeName>
    </Extension>
    <DeviceInfo />
  </Data>
</ReportNode>
<ReportNode type="Step">
<Data>
    <Name>Broadcast Message.Tap</Name>
    <Description />
    <StartTime>2023-06-05 14:10:18</StartTime>
    <Result>Done</Result>
    <Extension>
      <TestObject>
        <Repository>D:\BNI All\Mobile Keagenan Android\Lib_Repo_Excel_Keagenan_Mobile\Repo_Keagenan_Mobile\RP_KeagenanMobile_RiwayatPesan.tsr</Repository>
        <Path>
          <Object>
            <Type>Device</Type>
            <Name><![CDATA[Device]]></Name>
          </Object>
          <Object>
            <Type>App</Type>
            <Name><![CDATA[BNI Agen46]]></Name>
          </Object>
          <Object>
            <Type>MobileObject</Type>
            <Name><![CDATA[Broadcast Message]]></Name>
          </Object>
        </Path>
        <Operation>Tap</Operation>
        <Properties>
          <Property>
            <Name><![CDATA[resourceid]]></Name>
            <Value><![CDATA[]]></Value>
          </Property>
          <Property>
            <Name><![CDATA[nativeclass]]></Name>
            <Value><![CDATA[android.view.View]]></Value>
          </Property>
          <Property>
            <Name><![CDATA[mcindex]]></Name>
            <Value><![CDATA[18]]></Value>
          </Property>
          <Property>
            <Name><![CDATA[class]]></Name>
            <Value><![CDATA[View]]></Value>
          </Property>
          <Property>
            <Name><![CDATA[accessibilityid]]></Name>
            <Value><![CDATA[Broadcast Message]]></Value>
          </Property>
        </Properties>
      </TestObject>
      <IconKey>2942059282e44749a06ac7e476c1b694</IconKey>
      <IsPlainTextNodeName>True</IsPlainTextNodeName>
    </Extension>
    <DeviceInfo />
  </Data>
</ReportNode>
<ReportNode type="Step">
<Data>
    <Name>Test Broadcast Message 35298.Tap</Name>
    <Description />
    <StartTime>2023-06-05 14:10:45</StartTime>
    <Result>Done</Result>
    <Extension>
      <TestObject>
        <Repository>D:\BNI All\Mobile Keagenan Android\Lib_Repo_Excel_Keagenan_Mobile\Repo_Keagenan_Mobile\RP_KeagenanMobile_RiwayatPesan.tsr</Repository>
        <Path>
          <Object>
            <Type>Device</Type>
            <Name><![CDATA[Device]]></Name>
          </Object>
          <Object>
            <Type>App</Type>
            <Name><![CDATA[BNI Agen46]]></Name>
          </Object>
          <Object>
            <Type>MobileObject</Type>
            <Name><![CDATA[Test Broadcast Message 35298]]></Name>
          </Object>
        </Path>
        <Operation>Tap</Operation>
        <Properties>
          <Property>
            <Name><![CDATA[resourceid]]></Name>
            <Value><![CDATA[]]></Value>
          </Property>
          <Property>
            <Name><![CDATA[nativeclass]]></Name>
            <Value><![CDATA[android.view.View]]></Value>
          </Property>
          <Property>
            <Name><![CDATA[mcindex]]></Name>
            <Value><![CDATA[25]]></Value>
          </Property>
          <Property>
            <Name><![CDATA[class]]></Name>
            <Value><![CDATA[View]]></Value>
          </Property>
          <Property>
            <Name><![CDATA[accessibilityid]]></Name>
            <Value><![CDATA[Test Percobaan
Dari: 
35298
19/08/2021, 16:07]]></Value>
          </Property>
        </Properties>
      </TestObject>
      <IconKey>2942059282e44749a06ac7e476c1b694</IconKey>
      <IsPlainTextNodeName>True</IsPlainTextNodeName>
    </Extension>
    <DeviceInfo />
  </Data>
</ReportNode>
<Data>
    <Name>BNI Agen46 [version 2]</Name>
    <Description>&lt;table&gt;&lt;tr&gt;&lt;td style="text-align : left; font-size : 12px; font-weight : 600; "&gt;Package Name:&lt;/td&gt;&lt;td style="text-align : left; font-size : 12px; "&gt;id.co.bni.newagenbni46&lt;/td&gt;&lt;/tr&gt;&lt;tr&gt;&lt;td style="text-align : left; font-size : 12px; font-weight : 600; "&gt;Version:&lt;/td&gt;&lt;td style="text-align : left; font-size : 12px; "&gt;2&lt;/td&gt;&lt;/tr&gt;&lt;/table&gt;</Description>
    <StartTime>2023-06-05 14:09:29</StartTime>
    <Duration>95</Duration>
    <Result>Done</Result>
    <Extension>
      <TestObject>
        <Repository>Local</Repository>
        <Path>
          <Object>
            <Type>Device</Type>
            <Name><![CDATA[Device]]></Name>
          </Object>
          <Object>
            <Type>App</Type>
            <Name><![CDATA[BNI Agen46]]></Name>
          </Object>
        </Path>
        <Operation> [version 2]</Operation>
        <OperationData><![CDATA[<table><tr><td style="text-align : left; font-size : 12px; font-weight : 600; ">Package Name:</td><td style="text-align : left; font-size : 12px; ">id.co.bni.newagenbni46</td></tr><tr><td style="text-align : left; font-size : 12px; font-weight : 600; ">Version:</td><td style="text-align : left; font-size : 12px; ">2</td></tr></table>]]></OperationData>
        <Properties>
          <Property>
            <Name><![CDATA[instrumented]]></Name>
            <Value><![CDATA[False]]></Value>
          </Property>
          <Property>
            <Name><![CDATA[identifier]]></Name>
            <Value><![CDATA[id.co.bni.newagenbni46]]></Value>
          </Property>
        </Properties>
      </TestObject>
      <IconKey>091c96b8afe34f9fa25b1934c16b6015</IconKey>
      <IsPlainTextNodeName>True</IsPlainTextNodeName>
    </Extension>
  </Data>
</ReportNode>
<Data>
    <Name>Device [samsung SM-A525F]</Name>
    <Description>&lt;table&gt;&lt;tr&gt;&lt;td&gt;&lt;span style="text-align : left; font-size : 12px; font-weight : 600; "&gt;ID: &lt;/span&gt;&lt;span style="text-align : left; font-size : 12px; "&gt;RR8R8097ECH&lt;/span&gt;&lt;/td&gt;&lt;/tr&gt;&lt;tr&gt;&lt;td&gt;&lt;span style="text-align : left; font-size : 12px; font-weight : 600; "&gt;Manufacturer: &lt;/span&gt;&lt;span style="text-align : left; font-size : 12px; "&gt;samsung&lt;/span&gt;&lt;/td&gt;&lt;/tr&gt;&lt;tr&gt;&lt;td&gt;&lt;span style="text-align : left; font-size : 12px; font-weight : 600; "&gt;Model: &lt;/span&gt;&lt;span style="text-align : left; font-size : 12px; "&gt;SM-A525F&lt;/span&gt;&lt;/td&gt;&lt;/tr&gt;&lt;tr&gt;&lt;td&gt;&lt;span style="text-align : left; font-size : 12px; font-weight : 600; "&gt;OS Type: &lt;/span&gt;&lt;span style="text-align : left; font-size : 12px; "&gt;ANDROID&lt;/span&gt;&lt;/td&gt;&lt;/tr&gt;&lt;tr&gt;&lt;td&gt;&lt;span style="text-align : left; font-size : 12px; font-weight : 600; "&gt;OS Version: &lt;/span&gt;&lt;span style="text-align : left; font-size : 12px; "&gt;11&lt;/span&gt;&lt;/td&gt;&lt;/tr&gt;&lt;tr&gt;&lt;td&gt;&lt;span style="text-align : left; font-size : 12px; font-weight : 600; "&gt;Source: &lt;/span&gt;&lt;span style="text-align : left; font-size : 12px; "&gt;MC&lt;/span&gt;&lt;/td&gt;&lt;/tr&gt;&lt;/table&gt;</Description>
    <StartTime>2023-06-05 14:08:02</StartTime>
    <Duration>182</Duration>
    <Result>Done</Result>
    <Extension>
      <TestObject>
        <Repository>Local</Repository>
        <Path>
          <Object>
            <Type>Device</Type>
            <Name><![CDATA[Device]]></Name>
          </Object>
        </Path>
        <Operation> [samsung SM-A525F]</Operation>
        <OperationData><![CDATA[<table><tr><td><span style="text-align : left; font-size : 12px; font-weight : 600; ">ID: </span><span style="text-align : left; font-size : 12px; ">RR8R8097ECH</span></td></tr><tr><td><span style="text-align : left; font-size : 12px; font-weight : 600; ">Manufacturer: </span><span style="text-align : left; font-size : 12px; ">samsung</span></td></tr><tr><td><span style="text-align : left; font-size : 12px; font-weight : 600; ">Model: </span><span style="text-align : left; font-size : 12px; ">SM-A525F</span></td></tr><tr><td><span style="text-align : left; font-size : 12px; font-weight : 600; ">OS Type: </span><span style="text-align : left; font-size : 12px; ">ANDROID</span></td></tr><tr><td><span style="text-align : left; font-size : 12px; font-weight : 600; ">OS Version: </span><span style="text-align : left; font-size : 12px; ">11</span></td></tr><tr><td><span style="text-align : left; font-size : 12px; font-weight : 600; ">Source: </span><span style="text-align : left; font-size : 12px; ">MC</span></td></tr></table>]]></OperationData>
      </TestObject>
      <IconKey>1f0292796bf84524865c34d6243fdcd9</IconKey>
      <IsPlainTextNodeName>True</IsPlainTextNodeName>
    </Extension>
  </Data>
</ReportNode>
<Data>
    <Name>SMAG-0016 - Riwayat Pesan</Name>
    <Description />
    <StartTime>2023-06-05 14:07:48</StartTime>
    <Duration>196</Duration>
    <Result>Passed</Result>
    <Extension>
      <IconKey>fde8d33c0b6c460b90cf8818d6078b7e</IconKey>
      <IsPlainTextNodeName>True</IsPlainTextNodeName>
    </Extension>
    <Index>1</Index>
  </Data>
</ReportNode>
<ReportNode type="Iteration">
<ReportNode type="Step">
<Data>
    <Name>LoadFunctionLibrary</Name>
    <Description>LoadFunctionLibrary function passed</Description>
    <StartTime>2023-06-05 14:11:04</StartTime>
    <Result>Passed</Result>
    <Extension>
      <IconKey>6b3571f267314fd8800e5e9f08d7df52</IconKey>
      <IsPlainTextNodeName>True</IsPlainTextNodeName>
    </Extension>
    <DeviceInfo />
  </Data>
</ReportNode>
<ReportNode type="Step">
<Data>
    <Name>LoadFunctionLibrary</Name>
    <Description>LoadFunctionLibrary function passed</Description>
    <StartTime>2023-06-05 14:11:04</StartTime>
    <Result>Passed</Result>
    <Extension>
      <IconKey>6b3571f267314fd8800e5e9f08d7df52</IconKey>
      <IsPlainTextNodeName>True</IsPlainTextNodeName>
    </Extension>
    <DeviceInfo />
  </Data>
</ReportNode>
<ReportNode type="Step">
<Data>
    <Name>LoadFunctionLibrary</Name>
    <Description>LoadFunctionLibrary function passed</Description>
    <StartTime>2023-06-05 14:11:04</StartTime>
    <Result>Passed</Result>
    <Extension>
      <IconKey>6b3571f267314fd8800e5e9f08d7df52</IconKey>
      <IsPlainTextNodeName>True</IsPlainTextNodeName>
    </Extension>
    <DeviceInfo />
  </Data>
</ReportNode>
<ReportNode type="Step">
<Data>
    <Name>LoadFunctionLibrary</Name>
    <Description>LoadFunctionLibrary function passed</Description>
    <StartTime>2023-06-05 14:11:04</StartTime>
    <Result>Passed</Result>
    <Extension>
      <IconKey>6b3571f267314fd8800e5e9f08d7df52</IconKey>
      <IsPlainTextNodeName>True</IsPlainTextNodeName>
    </Extension>
    <DeviceInfo />
  </Data>
</ReportNode>
<ReportNode type="Step">
<Data>
    <Name>LoadFunctionLibrary</Name>
    <Description>LoadFunctionLibrary function passed</Description>
    <StartTime>2023-06-05 14:11:05</StartTime>
    <Result>Passed</Result>
    <Extension>
      <IconKey>6b3571f267314fd8800e5e9f08d7df52</IconKey>
      <IsPlainTextNodeName>True</IsPlainTextNodeName>
    </Extension>
    <DeviceInfo />
  </Data>
</ReportNode>
<ReportNode type="Step">
<Data>
    <Name>Stop action iteration replay</Name>
    <Description>Run stopped by user.</Description>
    <StartTime>2023-06-05 14:11:05</StartTime>
    <Result>Information</Result>
    <Extension>
      <IconKey>d71b363451e24b4f944926c546ee9002</IconKey>
      <IsPlainTextNodeName>True</IsPlainTextNodeName>
    </Extension>
  </Data>
</ReportNode>
<Data>
    <Name>SMAG-0016 - Riwayat Pesan</Name>
    <Description />
    <StartTime>2023-06-05 14:11:04</StartTime>
    <Duration>1</Duration>
    <Result>Passed</Result>
    <Extension>
      <IconKey>fde8d33c0b6c460b90cf8818d6078b7e</IconKey>
      <IsPlainTextNodeName>True</IsPlainTextNodeName>
    </Extension>
    <Index>2</Index>
    <TestedApplications />
  </Data>
</ReportNode>
<ReportNode type="Iteration">
<ReportNode type="Step">
<Data>
    <Name>LoadFunctionLibrary</Name>
    <Description>LoadFunctionLibrary function passed</Description>
    <StartTime>2023-06-05 14:11:05</StartTime>
    <Result>Passed</Result>
    <Extension>
      <IconKey>6b3571f267314fd8800e5e9f08d7df52</IconKey>
      <IsPlainTextNodeName>True</IsPlainTextNodeName>
    </Extension>
    <DeviceInfo />
  </Data>
</ReportNode>
<ReportNode type="Step">
<Data>
    <Name>LoadFunctionLibrary</Name>
    <Description>LoadFunctionLibrary function passed</Description>
    <StartTime>2023-06-05 14:11:05</StartTime>
    <Result>Passed</Result>
    <Extension>
      <IconKey>6b3571f267314fd8800e5e9f08d7df52</IconKey>
      <IsPlainTextNodeName>True</IsPlainTextNodeName>
    </Extension>
    <DeviceInfo />
  </Data>
</ReportNode>
<ReportNode type="Step">
<Data>
    <Name>LoadFunctionLibrary</Name>
    <Description>LoadFunctionLibrary function passed</Description>
    <StartTime>2023-06-05 14:11:05</StartTime>
    <Result>Passed</Result>
    <Extension>
      <IconKey>6b3571f267314fd8800e5e9f08d7df52</IconKey>
      <IsPlainTextNodeName>True</IsPlainTextNodeName>
    </Extension>
    <DeviceInfo />
  </Data>
</ReportNode>
<ReportNode type="Step">
<Data>
    <Name>LoadFunctionLibrary</Name>
    <Description>LoadFunctionLibrary function passed</Description>
    <StartTime>2023-06-05 14:11:05</StartTime>
    <Result>Passed</Result>
    <Extension>
      <IconKey>6b3571f267314fd8800e5e9f08d7df52</IconKey>
      <IsPlainTextNodeName>True</IsPlainTextNodeName>
    </Extension>
    <DeviceInfo />
  </Data>
</ReportNode>
<ReportNode type="Step">
<Data>
    <Name>LoadFunctionLibrary</Name>
    <Description>LoadFunctionLibrary function passed</Description>
    <StartTime>2023-06-05 14:11:05</StartTime>
    <Result>Passed</Result>
    <Extension>
      <IconKey>6b3571f267314fd8800e5e9f08d7df52</IconKey>
      <IsPlainTextNodeName>True</IsPlainTextNodeName>
    </Extension>
    <DeviceInfo />
  </Data>
</ReportNode>
<ReportNode type="Step">
<Data>
    <Name>Stop action iteration replay</Name>
    <Description>Run stopped by user.</Description>
    <StartTime>2023-06-05 14:11:05</StartTime>
    <Result>Information</Result>
    <Extension>
      <IconKey>d71b363451e24b4f944926c546ee9002</IconKey>
      <IsPlainTextNodeName>True</IsPlainTextNodeName>
    </Extension>
  </Data>
</ReportNode>
<Data>
    <Name>SMAG-0016 - Riwayat Pesan</Name>
    <Description />
    <StartTime>2023-06-05 14:11:05</StartTime>
    <Duration>0</Duration>
    <Result>Passed</Result>
    <Extension>
      <IconKey>fde8d33c0b6c460b90cf8818d6078b7e</IconKey>
      <IsPlainTextNodeName>True</IsPlainTextNodeName>
    </Extension>
    <Index>3</Index>
    <TestedApplications />
  </Data>
</ReportNode>
<ReportNode type="Iteration">
<ReportNode type="Step">
<Data>
    <Name>LoadFunctionLibrary</Name>
    <Description>LoadFunctionLibrary function passed</Description>
    <StartTime>2023-06-05 14:11:05</StartTime>
    <Result>Passed</Result>
    <Extension>
      <IconKey>6b3571f267314fd8800e5e9f08d7df52</IconKey>
      <IsPlainTextNodeName>True</IsPlainTextNodeName>
    </Extension>
    <DeviceInfo />
  </Data>
</ReportNode>
<ReportNode type="Step">
<Data>
    <Name>LoadFunctionLibrary</Name>
    <Description>LoadFunctionLibrary function passed</Description>
    <StartTime>2023-06-05 14:11:06</StartTime>
    <Result>Passed</Result>
    <Extension>
      <IconKey>6b3571f267314fd8800e5e9f08d7df52</IconKey>
      <IsPlainTextNodeName>True</IsPlainTextNodeName>
    </Extension>
    <DeviceInfo />
  </Data>
</ReportNode>
<ReportNode type="Step">
<Data>
    <Name>LoadFunctionLibrary</Name>
    <Description>LoadFunctionLibrary function passed</Description>
    <StartTime>2023-06-05 14:11:06</StartTime>
    <Result>Passed</Result>
    <Extension>
      <IconKey>6b3571f267314fd8800e5e9f08d7df52</IconKey>
      <IsPlainTextNodeName>True</IsPlainTextNodeName>
    </Extension>
    <DeviceInfo />
  </Data>
</ReportNode>
<ReportNode type="Step">
<Data>
    <Name>LoadFunctionLibrary</Name>
    <Description>LoadFunctionLibrary function passed</Description>
    <StartTime>2023-06-05 14:11:06</StartTime>
    <Result>Passed</Result>
    <Extension>
      <IconKey>6b3571f267314fd8800e5e9f08d7df52</IconKey>
      <IsPlainTextNodeName>True</IsPlainTextNodeName>
    </Extension>
    <DeviceInfo />
  </Data>
</ReportNode>
<ReportNode type="Step">
<Data>
    <Name>LoadFunctionLibrary</Name>
    <Description>LoadFunctionLibrary function passed</Description>
    <StartTime>2023-06-05 14:11:06</StartTime>
    <Result>Passed</Result>
    <Extension>
      <IconKey>6b3571f267314fd8800e5e9f08d7df52</IconKey>
      <IsPlainTextNodeName>True</IsPlainTextNodeName>
    </Extension>
    <DeviceInfo />
  </Data>
</ReportNode>
<ReportNode type="Step">
<Data>
    <Name>Stop action iteration replay</Name>
    <Description>Run stopped by user.</Description>
    <StartTime>2023-06-05 14:11:06</StartTime>
    <Result>Information</Result>
    <Extension>
      <IconKey>d71b363451e24b4f944926c546ee9002</IconKey>
      <IsPlainTextNodeName>True</IsPlainTextNodeName>
    </Extension>
  </Data>
</ReportNode>
<Data>
    <Name>SMAG-0016 - Riwayat Pesan</Name>
    <Description />
    <StartTime>2023-06-05 14:11:05</StartTime>
    <Duration>1</Duration>
    <Result>Passed</Result>
    <Extension>
      <IconKey>fde8d33c0b6c460b90cf8818d6078b7e</IconKey>
      <IsPlainTextNodeName>True</IsPlainTextNodeName>
    </Extension>
    <Index>4</Index>
    <TestedApplications />
  </Data>
</ReportNode>
<ReportNode type="Iteration">
<ReportNode type="Step">
<Data>
    <Name>LoadFunctionLibrary</Name>
    <Description>LoadFunctionLibrary function passed</Description>
    <StartTime>2023-06-05 14:11:06</StartTime>
    <Result>Passed</Result>
    <Extension>
      <IconKey>6b3571f267314fd8800e5e9f08d7df52</IconKey>
      <IsPlainTextNodeName>True</IsPlainTextNodeName>
    </Extension>
    <DeviceInfo />
  </Data>
</ReportNode>
<ReportNode type="Step">
<Data>
    <Name>LoadFunctionLibrary</Name>
    <Description>LoadFunctionLibrary function passed</Description>
    <StartTime>2023-06-05 14:11:06</StartTime>
    <Result>Passed</Result>
    <Extension>
      <IconKey>6b3571f267314fd8800e5e9f08d7df52</IconKey>
      <IsPlainTextNodeName>True</IsPlainTextNodeName>
    </Extension>
    <DeviceInfo />
  </Data>
</ReportNode>
<ReportNode type="Step">
<Data>
    <Name>LoadFunctionLibrary</Name>
    <Description>LoadFunctionLibrary function passed</Description>
    <StartTime>2023-06-05 14:11:06</StartTime>
    <Result>Passed</Result>
    <Extension>
      <IconKey>6b3571f267314fd8800e5e9f08d7df52</IconKey>
      <IsPlainTextNodeName>True</IsPlainTextNodeName>
    </Extension>
    <DeviceInfo />
  </Data>
</ReportNode>
<ReportNode type="Step">
<Data>
    <Name>LoadFunctionLibrary</Name>
    <Description>LoadFunctionLibrary function passed</Description>
    <StartTime>2023-06-05 14:11:06</StartTime>
    <Result>Passed</Result>
    <Extension>
      <IconKey>6b3571f267314fd8800e5e9f08d7df52</IconKey>
      <IsPlainTextNodeName>True</IsPlainTextNodeName>
    </Extension>
    <DeviceInfo />
  </Data>
</ReportNode>
<ReportNode type="Step">
<Data>
    <Name>LoadFunctionLibrary</Name>
    <Description>LoadFunctionLibrary function passed</Description>
    <StartTime>2023-06-05 14:11:06</StartTime>
    <Result>Passed</Result>
    <Extension>
      <IconKey>6b3571f267314fd8800e5e9f08d7df52</IconKey>
      <IsPlainTextNodeName>True</IsPlainTextNodeName>
    </Extension>
    <DeviceInfo />
  </Data>
</ReportNode>
<ReportNode type="Step">
<Data>
    <Name>Stop action iteration replay</Name>
    <Description>Run stopped by user.</Description>
    <StartTime>2023-06-05 14:11:06</StartTime>
    <Result>Information</Result>
    <Extension>
      <IconKey>d71b363451e24b4f944926c546ee9002</IconKey>
      <IsPlainTextNodeName>True</IsPlainTextNodeName>
    </Extension>
  </Data>
</ReportNode>
<Data>
    <Name>SMAG-0016 - Riwayat Pesan</Name>
    <Description />
    <StartTime>2023-06-05 14:11:06</StartTime>
    <Duration>0</Duration>
    <Result>Passed</Result>
    <Extension>
      <IconKey>fde8d33c0b6c460b90cf8818d6078b7e</IconKey>
      <IsPlainTextNodeName>True</IsPlainTextNodeName>
    </Extension>
    <Index>5</Index>
    <TestedApplications />
  </Data>
</ReportNode>
<ReportNode type="Iteration">
<ReportNode type="Step">
<Data>
    <Name>LoadFunctionLibrary</Name>
    <Description>LoadFunctionLibrary function passed</Description>
    <StartTime>2023-06-05 14:11:07</StartTime>
    <Result>Passed</Result>
    <Extension>
      <IconKey>6b3571f267314fd8800e5e9f08d7df52</IconKey>
      <IsPlainTextNodeName>True</IsPlainTextNodeName>
    </Extension>
    <DeviceInfo />
  </Data>
</ReportNode>
<ReportNode type="Step">
<Data>
    <Name>LoadFunctionLibrary</Name>
    <Description>LoadFunctionLibrary function passed</Description>
    <StartTime>2023-06-05 14:11:07</StartTime>
    <Result>Passed</Result>
    <Extension>
      <IconKey>6b3571f267314fd8800e5e9f08d7df52</IconKey>
      <IsPlainTextNodeName>True</IsPlainTextNodeName>
    </Extension>
    <DeviceInfo />
  </Data>
</ReportNode>
<ReportNode type="Step">
<Data>
    <Name>LoadFunctionLibrary</Name>
    <Description>LoadFunctionLibrary function passed</Description>
    <StartTime>2023-06-05 14:11:07</StartTime>
    <Result>Passed</Result>
    <Extension>
      <IconKey>6b3571f267314fd8800e5e9f08d7df52</IconKey>
      <IsPlainTextNodeName>True</IsPlainTextNodeName>
    </Extension>
    <DeviceInfo />
  </Data>
</ReportNode>
<ReportNode type="Step">
<Data>
    <Name>LoadFunctionLibrary</Name>
    <Description>LoadFunctionLibrary function passed</Description>
    <StartTime>2023-06-05 14:11:07</StartTime>
    <Result>Passed</Result>
    <Extension>
      <IconKey>6b3571f267314fd8800e5e9f08d7df52</IconKey>
      <IsPlainTextNodeName>True</IsPlainTextNodeName>
    </Extension>
    <DeviceInfo />
  </Data>
</ReportNode>
<ReportNode type="Step">
<Data>
    <Name>LoadFunctionLibrary</Name>
    <Description>LoadFunctionLibrary function passed</Description>
    <StartTime>2023-06-05 14:11:07</StartTime>
    <Result>Passed</Result>
    <Extension>
      <IconKey>6b3571f267314fd8800e5e9f08d7df52</IconKey>
      <IsPlainTextNodeName>True</IsPlainTextNodeName>
    </Extension>
    <DeviceInfo />
  </Data>
</ReportNode>
<ReportNode type="Step">
<Data>
    <Name>Stop action iteration replay</Name>
    <Description>Run stopped by user.</Description>
    <StartTime>2023-06-05 14:11:07</StartTime>
    <Result>Information</Result>
    <Extension>
      <IconKey>d71b363451e24b4f944926c546ee9002</IconKey>
      <IsPlainTextNodeName>True</IsPlainTextNodeName>
    </Extension>
  </Data>
</ReportNode>
<Data>
    <Name>SMAG-0016 - Riwayat Pesan</Name>
    <Description />
    <StartTime>2023-06-05 14:11:06</StartTime>
    <Duration>1</Duration>
    <Result>Passed</Result>
    <Extension>
      <IconKey>fde8d33c0b6c460b90cf8818d6078b7e</IconKey>
      <IsPlainTextNodeName>True</IsPlainTextNodeName>
    </Extension>
    <Index>6</Index>
    <TestedApplications />
  </Data>
</ReportNode>
<ReportNode type="Iteration">
<ReportNode type="Step">
<Data>
    <Name>LoadFunctionLibrary</Name>
    <Description>LoadFunctionLibrary function passed</Description>
    <StartTime>2023-06-05 14:11:07</StartTime>
    <Result>Passed</Result>
    <Extension>
      <IconKey>6b3571f267314fd8800e5e9f08d7df52</IconKey>
      <IsPlainTextNodeName>True</IsPlainTextNodeName>
    </Extension>
    <DeviceInfo />
  </Data>
</ReportNode>
<ReportNode type="Step">
<Data>
    <Name>LoadFunctionLibrary</Name>
    <Description>LoadFunctionLibrary function passed</Description>
    <StartTime>2023-06-05 14:11:07</StartTime>
    <Result>Passed</Result>
    <Extension>
      <IconKey>6b3571f267314fd8800e5e9f08d7df52</IconKey>
      <IsPlainTextNodeName>True</IsPlainTextNodeName>
    </Extension>
    <DeviceInfo />
  </Data>
</ReportNode>
<ReportNode type="Step">
<Data>
    <Name>LoadFunctionLibrary</Name>
    <Description>LoadFunctionLibrary function passed</Description>
    <StartTime>2023-06-05 14:11:07</StartTime>
    <Result>Passed</Result>
    <Extension>
      <IconKey>6b3571f267314fd8800e5e9f08d7df52</IconKey>
      <IsPlainTextNodeName>True</IsPlainTextNodeName>
    </Extension>
    <DeviceInfo />
  </Data>
</ReportNode>
<ReportNode type="Step">
<Data>
    <Name>LoadFunctionLibrary</Name>
    <Description>LoadFunctionLibrary function passed</Description>
    <StartTime>2023-06-05 14:11:07</StartTime>
    <Result>Passed</Result>
    <Extension>
      <IconKey>6b3571f267314fd8800e5e9f08d7df52</IconKey>
      <IsPlainTextNodeName>True</IsPlainTextNodeName>
    </Extension>
    <DeviceInfo />
  </Data>
</ReportNode>
<ReportNode type="Step">
<Data>
    <Name>LoadFunctionLibrary</Name>
    <Description>LoadFunctionLibrary function passed</Description>
    <StartTime>2023-06-05 14:11:07</StartTime>
    <Result>Passed</Result>
    <Extension>
      <IconKey>6b3571f267314fd8800e5e9f08d7df52</IconKey>
      <IsPlainTextNodeName>True</IsPlainTextNodeName>
    </Extension>
    <DeviceInfo />
  </Data>
</ReportNode>
<ReportNode type="Step">
<Data>
    <Name>Stop action iteration replay</Name>
    <Description>Run stopped by user.</Description>
    <StartTime>2023-06-05 14:11:08</StartTime>
    <Result>Information</Result>
    <Extension>
      <IconKey>d71b363451e24b4f944926c546ee9002</IconKey>
      <IsPlainTextNodeName>True</IsPlainTextNodeName>
    </Extension>
  </Data>
</ReportNode>
<Data>
    <Name>SMAG-0016 - Riwayat Pesan</Name>
    <Description />
    <StartTime>2023-06-05 14:11:07</StartTime>
    <Duration>1</Duration>
    <Result>Passed</Result>
    <Extension>
      <IconKey>fde8d33c0b6c460b90cf8818d6078b7e</IconKey>
      <IsPlainTextNodeName>True</IsPlainTextNodeName>
    </Extension>
    <Index>7</Index>
    <TestedApplications />
  </Data>
</ReportNode>
<ReportNode type="Iteration">
<ReportNode type="Step">
<Data>
    <Name>LoadFunctionLibrary</Name>
    <Description>LoadFunctionLibrary function passed</Description>
    <StartTime>2023-06-05 14:11:08</StartTime>
    <Result>Passed</Result>
    <Extension>
      <IconKey>6b3571f267314fd8800e5e9f08d7df52</IconKey>
      <IsPlainTextNodeName>True</IsPlainTextNodeName>
    </Extension>
    <DeviceInfo />
  </Data>
</ReportNode>
<ReportNode type="Step">
<Data>
    <Name>LoadFunctionLibrary</Name>
    <Description>LoadFunctionLibrary function passed</Description>
    <StartTime>2023-06-05 14:11:08</StartTime>
    <Result>Passed</Result>
    <Extension>
      <IconKey>6b3571f267314fd8800e5e9f08d7df52</IconKey>
      <IsPlainTextNodeName>True</IsPlainTextNodeName>
    </Extension>
    <DeviceInfo />
  </Data>
</ReportNode>
<ReportNode type="Step">
<Data>
    <Name>LoadFunctionLibrary</Name>
    <Description>LoadFunctionLibrary function passed</Description>
    <StartTime>2023-06-05 14:11:08</StartTime>
    <Result>Passed</Result>
    <Extension>
      <IconKey>6b3571f267314fd8800e5e9f08d7df52</IconKey>
      <IsPlainTextNodeName>True</IsPlainTextNodeName>
    </Extension>
    <DeviceInfo />
  </Data>
</ReportNode>
<ReportNode type="Step">
<Data>
    <Name>LoadFunctionLibrary</Name>
    <Description>LoadFunctionLibrary function passed</Description>
    <StartTime>2023-06-05 14:11:08</StartTime>
    <Result>Passed</Result>
    <Extension>
      <IconKey>6b3571f267314fd8800e5e9f08d7df52</IconKey>
      <IsPlainTextNodeName>True</IsPlainTextNodeName>
    </Extension>
    <DeviceInfo />
  </Data>
</ReportNode>
<ReportNode type="Step">
<Data>
    <Name>LoadFunctionLibrary</Name>
    <Description>LoadFunctionLibrary function passed</Description>
    <StartTime>2023-06-05 14:11:08</StartTime>
    <Result>Passed</Result>
    <Extension>
      <IconKey>6b3571f267314fd8800e5e9f08d7df52</IconKey>
      <IsPlainTextNodeName>True</IsPlainTextNodeName>
    </Extension>
    <DeviceInfo />
  </Data>
</ReportNode>
<ReportNode type="Step">
<Data>
    <Name>Stop action iteration replay</Name>
    <Description>Run stopped by user.</Description>
    <StartTime>2023-06-05 14:11:08</StartTime>
    <Result>Information</Result>
    <Extension>
      <IconKey>d71b363451e24b4f944926c546ee9002</IconKey>
      <IsPlainTextNodeName>True</IsPlainTextNodeName>
    </Extension>
  </Data>
</ReportNode>
<Data>
    <Name>SMAG-0016 - Riwayat Pesan</Name>
    <Description />
    <StartTime>2023-06-05 14:11:08</StartTime>
    <Duration>0</Duration>
    <Result>Passed</Result>
    <Extension>
      <IconKey>fde8d33c0b6c460b90cf8818d6078b7e</IconKey>
      <IsPlainTextNodeName>True</IsPlainTextNodeName>
    </Extension>
    <Index>8</Index>
    <TestedApplications />
  </Data>
</ReportNode>
<ReportNode type="Iteration">
<ReportNode type="Step">
<Data>
    <Name>LoadFunctionLibrary</Name>
    <Description>LoadFunctionLibrary function passed</Description>
    <StartTime>2023-06-05 14:11:08</StartTime>
    <Result>Passed</Result>
    <Extension>
      <IconKey>6b3571f267314fd8800e5e9f08d7df52</IconKey>
      <IsPlainTextNodeName>True</IsPlainTextNodeName>
    </Extension>
    <DeviceInfo />
  </Data>
</ReportNode>
<ReportNode type="Step">
<Data>
    <Name>LoadFunctionLibrary</Name>
    <Description>LoadFunctionLibrary function passed</Description>
    <StartTime>2023-06-05 14:11:08</StartTime>
    <Result>Passed</Result>
    <Extension>
      <IconKey>6b3571f267314fd8800e5e9f08d7df52</IconKey>
      <IsPlainTextNodeName>True</IsPlainTextNodeName>
    </Extension>
    <DeviceInfo />
  </Data>
</ReportNode>
<ReportNode type="Step">
<Data>
    <Name>LoadFunctionLibrary</Name>
    <Description>LoadFunctionLibrary function passed</Description>
    <StartTime>2023-06-05 14:11:08</StartTime>
    <Result>Passed</Result>
    <Extension>
      <IconKey>6b3571f267314fd8800e5e9f08d7df52</IconKey>
      <IsPlainTextNodeName>True</IsPlainTextNodeName>
    </Extension>
    <DeviceInfo />
  </Data>
</ReportNode>
<ReportNode type="Step">
<Data>
    <Name>LoadFunctionLibrary</Name>
    <Description>LoadFunctionLibrary function passed</Description>
    <StartTime>2023-06-05 14:11:08</StartTime>
    <Result>Passed</Result>
    <Extension>
      <IconKey>6b3571f267314fd8800e5e9f08d7df52</IconKey>
      <IsPlainTextNodeName>True</IsPlainTextNodeName>
    </Extension>
    <DeviceInfo />
  </Data>
</ReportNode>
<ReportNode type="Step">
<Data>
    <Name>LoadFunctionLibrary</Name>
    <Description>LoadFunctionLibrary function passed</Description>
    <StartTime>2023-06-05 14:11:08</StartTime>
    <Result>Passed</Result>
    <Extension>
      <IconKey>6b3571f267314fd8800e5e9f08d7df52</IconKey>
      <IsPlainTextNodeName>True</IsPlainTextNodeName>
    </Extension>
    <DeviceInfo />
  </Data>
</ReportNode>
<ReportNode type="Step">
<Data>
    <Name>Stop action iteration replay</Name>
    <Description>Run stopped by user.</Description>
    <StartTime>2023-06-05 14:11:09</StartTime>
    <Result>Information</Result>
    <Extension>
      <IconKey>d71b363451e24b4f944926c546ee9002</IconKey>
      <IsPlainTextNodeName>True</IsPlainTextNodeName>
    </Extension>
  </Data>
</ReportNode>
<Data>
    <Name>SMAG-0016 - Riwayat Pesan</Name>
    <Description />
    <StartTime>2023-06-05 14:11:08</StartTime>
    <Duration>1</Duration>
    <Result>Passed</Result>
    <Extension>
      <IconKey>fde8d33c0b6c460b90cf8818d6078b7e</IconKey>
      <IsPlainTextNodeName>True</IsPlainTextNodeName>
    </Extension>
    <Index>9</Index>
    <TestedApplications />
  </Data>
</ReportNode>
<ReportNode type="Iteration">
<ReportNode type="Step">
<Data>
    <Name>LoadFunctionLibrary</Name>
    <Description>LoadFunctionLibrary function passed</Description>
    <StartTime>2023-06-05 14:11:09</StartTime>
    <Result>Passed</Result>
    <Extension>
      <IconKey>6b3571f267314fd8800e5e9f08d7df52</IconKey>
      <IsPlainTextNodeName>True</IsPlainTextNodeName>
    </Extension>
    <DeviceInfo />
  </Data>
</ReportNode>
<ReportNode type="Step">
<Data>
    <Name>LoadFunctionLibrary</Name>
    <Description>LoadFunctionLibrary function passed</Description>
    <StartTime>2023-06-05 14:11:09</StartTime>
    <Result>Passed</Result>
    <Extension>
      <IconKey>6b3571f267314fd8800e5e9f08d7df52</IconKey>
      <IsPlainTextNodeName>True</IsPlainTextNodeName>
    </Extension>
    <DeviceInfo />
  </Data>
</ReportNode>
<ReportNode type="Step">
<Data>
    <Name>LoadFunctionLibrary</Name>
    <Description>LoadFunctionLibrary function passed</Description>
    <StartTime>2023-06-05 14:11:09</StartTime>
    <Result>Passed</Result>
    <Extension>
      <IconKey>6b3571f267314fd8800e5e9f08d7df52</IconKey>
      <IsPlainTextNodeName>True</IsPlainTextNodeName>
    </Extension>
    <DeviceInfo />
  </Data>
</ReportNode>
<ReportNode type="Step">
<Data>
    <Name>LoadFunctionLibrary</Name>
    <Description>LoadFunctionLibrary function passed</Description>
    <StartTime>2023-06-05 14:11:09</StartTime>
    <Result>Passed</Result>
    <Extension>
      <IconKey>6b3571f267314fd8800e5e9f08d7df52</IconKey>
      <IsPlainTextNodeName>True</IsPlainTextNodeName>
    </Extension>
    <DeviceInfo />
  </Data>
</ReportNode>
<ReportNode type="Step">
<Data>
    <Name>LoadFunctionLibrary</Name>
    <Description>LoadFunctionLibrary function passed</Description>
    <StartTime>2023-06-05 14:11:09</StartTime>
    <Result>Passed</Result>
    <Extension>
      <IconKey>6b3571f267314fd8800e5e9f08d7df52</IconKey>
      <IsPlainTextNodeName>True</IsPlainTextNodeName>
    </Extension>
    <DeviceInfo />
  </Data>
</ReportNode>
<ReportNode type="Step">
<Data>
    <Name>Stop action iteration replay</Name>
    <Description>Run stopped by user.</Description>
    <StartTime>2023-06-05 14:11:09</StartTime>
    <Result>Information</Result>
    <Extension>
      <IconKey>d71b363451e24b4f944926c546ee9002</IconKey>
      <IsPlainTextNodeName>True</IsPlainTextNodeName>
    </Extension>
  </Data>
</ReportNode>
<Data>
    <Name>SMAG-0016 - Riwayat Pesan</Name>
    <Description />
    <StartTime>2023-06-05 14:11:09</StartTime>
    <Duration>0</Duration>
    <Result>Passed</Result>
    <Extension>
      <IconKey>fde8d33c0b6c460b90cf8818d6078b7e</IconKey>
      <IsPlainTextNodeName>True</IsPlainTextNodeName>
    </Extension>
    <Index>10</Index>
    <TestedApplications />
  </Data>
</ReportNode>
<ReportNode type="Iteration">
<ReportNode type="Step">
<Data>
    <Name>LoadFunctionLibrary</Name>
    <Description>LoadFunctionLibrary function passed</Description>
    <StartTime>2023-06-05 14:11:09</StartTime>
    <Result>Passed</Result>
    <Extension>
      <IconKey>6b3571f267314fd8800e5e9f08d7df52</IconKey>
      <IsPlainTextNodeName>True</IsPlainTextNodeName>
    </Extension>
    <DeviceInfo />
  </Data>
</ReportNode>
<ReportNode type="Step">
<Data>
    <Name>LoadFunctionLibrary</Name>
    <Description>LoadFunctionLibrary function passed</Description>
    <StartTime>2023-06-05 14:11:09</StartTime>
    <Result>Passed</Result>
    <Extension>
      <IconKey>6b3571f267314fd8800e5e9f08d7df52</IconKey>
      <IsPlainTextNodeName>True</IsPlainTextNodeName>
    </Extension>
    <DeviceInfo />
  </Data>
</ReportNode>
<ReportNode type="Step">
<Data>
    <Name>LoadFunctionLibrary</Name>
    <Description>LoadFunctionLibrary function passed</Description>
    <StartTime>2023-06-05 14:11:09</StartTime>
    <Result>Passed</Result>
    <Extension>
      <IconKey>6b3571f267314fd8800e5e9f08d7df52</IconKey>
      <IsPlainTextNodeName>True</IsPlainTextNodeName>
    </Extension>
    <DeviceInfo />
  </Data>
</ReportNode>
<ReportNode type="Step">
<Data>
    <Name>LoadFunctionLibrary</Name>
    <Description>LoadFunctionLibrary function passed</Description>
    <StartTime>2023-06-05 14:11:09</StartTime>
    <Result>Passed</Result>
    <Extension>
      <IconKey>6b3571f267314fd8800e5e9f08d7df52</IconKey>
      <IsPlainTextNodeName>True</IsPlainTextNodeName>
    </Extension>
    <DeviceInfo />
  </Data>
</ReportNode>
<ReportNode type="Step">
<Data>
    <Name>LoadFunctionLibrary</Name>
    <Description>LoadFunctionLibrary function passed</Description>
    <StartTime>2023-06-05 14:11:09</StartTime>
    <Result>Passed</Result>
    <Extension>
      <IconKey>6b3571f267314fd8800e5e9f08d7df52</IconKey>
      <IsPlainTextNodeName>True</IsPlainTextNodeName>
    </Extension>
    <DeviceInfo />
  </Data>
</ReportNode>
<ReportNode type="Step">
<Data>
    <Name>Stop action iteration replay</Name>
    <Description>Run stopped by user.</Description>
    <StartTime>2023-06-05 14:11:10</StartTime>
    <Result>Information</Result>
    <Extension>
      <IconKey>d71b363451e24b4f944926c546ee9002</IconKey>
      <IsPlainTextNodeName>True</IsPlainTextNodeName>
    </Extension>
  </Data>
</ReportNode>
<Data>
    <Name>SMAG-0016 - Riwayat Pesan</Name>
    <Description />
    <StartTime>2023-06-05 14:11:09</StartTime>
    <Duration>1</Duration>
    <Result>Passed</Result>
    <Extension>
      <IconKey>fde8d33c0b6c460b90cf8818d6078b7e</IconKey>
      <IsPlainTextNodeName>True</IsPlainTextNodeName>
    </Extension>
    <Index>11</Index>
    <TestedApplications />
  </Data>
</ReportNode>
<ReportNode type="Iteration">
<ReportNode type="Step">
<Data>
    <Name>LoadFunctionLibrary</Name>
    <Description>LoadFunctionLibrary function passed</Description>
    <StartTime>2023-06-05 14:11:10</StartTime>
    <Result>Passed</Result>
    <Extension>
      <IconKey>6b3571f267314fd8800e5e9f08d7df52</IconKey>
      <IsPlainTextNodeName>True</IsPlainTextNodeName>
    </Extension>
    <DeviceInfo />
  </Data>
</ReportNode>
<ReportNode type="Step">
<Data>
    <Name>LoadFunctionLibrary</Name>
    <Description>LoadFunctionLibrary function passed</Description>
    <StartTime>2023-06-05 14:11:10</StartTime>
    <Result>Passed</Result>
    <Extension>
      <IconKey>6b3571f267314fd8800e5e9f08d7df52</IconKey>
      <IsPlainTextNodeName>True</IsPlainTextNodeName>
    </Extension>
    <DeviceInfo />
  </Data>
</ReportNode>
<ReportNode type="Step">
<Data>
    <Name>LoadFunctionLibrary</Name>
    <Description>LoadFunctionLibrary function passed</Description>
    <StartTime>2023-06-05 14:11:10</StartTime>
    <Result>Passed</Result>
    <Extension>
      <IconKey>6b3571f267314fd8800e5e9f08d7df52</IconKey>
      <IsPlainTextNodeName>True</IsPlainTextNodeName>
    </Extension>
    <DeviceInfo />
  </Data>
</ReportNode>
<ReportNode type="Step">
<Data>
    <Name>LoadFunctionLibrary</Name>
    <Description>LoadFunctionLibrary function passed</Description>
    <StartTime>2023-06-05 14:11:10</StartTime>
    <Result>Passed</Result>
    <Extension>
      <IconKey>6b3571f267314fd8800e5e9f08d7df52</IconKey>
      <IsPlainTextNodeName>True</IsPlainTextNodeName>
    </Extension>
    <DeviceInfo />
  </Data>
</ReportNode>
<ReportNode type="Step">
<Data>
    <Name>LoadFunctionLibrary</Name>
    <Description>LoadFunctionLibrary function passed</Description>
    <StartTime>2023-06-05 14:11:10</StartTime>
    <Result>Passed</Result>
    <Extension>
      <IconKey>6b3571f267314fd8800e5e9f08d7df52</IconKey>
      <IsPlainTextNodeName>True</IsPlainTextNodeName>
    </Extension>
    <DeviceInfo />
  </Data>
</ReportNode>
<ReportNode type="Step">
<Data>
    <Name>Stop action iteration replay</Name>
    <Description>Run stopped by user.</Description>
    <StartTime>2023-06-05 14:11:10</StartTime>
    <Result>Information</Result>
    <Extension>
      <IconKey>d71b363451e24b4f944926c546ee9002</IconKey>
      <IsPlainTextNodeName>True</IsPlainTextNodeName>
    </Extension>
  </Data>
</ReportNode>
<Data>
    <Name>SMAG-0016 - Riwayat Pesan</Name>
    <Description />
    <StartTime>2023-06-05 14:11:10</StartTime>
    <Duration>0</Duration>
    <Result>Passed</Result>
    <Extension>
      <IconKey>fde8d33c0b6c460b90cf8818d6078b7e</IconKey>
      <IsPlainTextNodeName>True</IsPlainTextNodeName>
    </Extension>
    <Index>12</Index>
    <TestedApplications />
  </Data>
</ReportNode>
<ReportNode type="Iteration">
<ReportNode type="Step">
<Data>
    <Name>LoadFunctionLibrary</Name>
    <Description>LoadFunctionLibrary function passed</Description>
    <StartTime>2023-06-05 14:11:11</StartTime>
    <Result>Passed</Result>
    <Extension>
      <IconKey>6b3571f267314fd8800e5e9f08d7df52</IconKey>
      <IsPlainTextNodeName>True</IsPlainTextNodeName>
    </Extension>
    <DeviceInfo />
  </Data>
</ReportNode>
<ReportNode type="Step">
<Data>
    <Name>LoadFunctionLibrary</Name>
    <Description>LoadFunctionLibrary function passed</Description>
    <StartTime>2023-06-05 14:11:11</StartTime>
    <Result>Passed</Result>
    <Extension>
      <IconKey>6b3571f267314fd8800e5e9f08d7df52</IconKey>
      <IsPlainTextNodeName>True</IsPlainTextNodeName>
    </Extension>
    <DeviceInfo />
  </Data>
</ReportNode>
<ReportNode type="Step">
<Data>
    <Name>LoadFunctionLibrary</Name>
    <Description>LoadFunctionLibrary function passed</Description>
    <StartTime>2023-06-05 14:11:11</StartTime>
    <Result>Passed</Result>
    <Extension>
      <IconKey>6b3571f267314fd8800e5e9f08d7df52</IconKey>
      <IsPlainTextNodeName>True</IsPlainTextNodeName>
    </Extension>
    <DeviceInfo />
  </Data>
</ReportNode>
<ReportNode type="Step">
<Data>
    <Name>LoadFunctionLibrary</Name>
    <Description>LoadFunctionLibrary function passed</Description>
    <StartTime>2023-06-05 14:11:11</StartTime>
    <Result>Passed</Result>
    <Extension>
      <IconKey>6b3571f267314fd8800e5e9f08d7df52</IconKey>
      <IsPlainTextNodeName>True</IsPlainTextNodeName>
    </Extension>
    <DeviceInfo />
  </Data>
</ReportNode>
<ReportNode type="Step">
<Data>
    <Name>LoadFunctionLibrary</Name>
    <Description>LoadFunctionLibrary function passed</Description>
    <StartTime>2023-06-05 14:11:11</StartTime>
    <Result>Passed</Result>
    <Extension>
      <IconKey>6b3571f267314fd8800e5e9f08d7df52</IconKey>
      <IsPlainTextNodeName>True</IsPlainTextNodeName>
    </Extension>
    <DeviceInfo />
  </Data>
</ReportNode>
<ReportNode type="Step">
<Data>
    <Name>Stop action iteration replay</Name>
    <Description>Run stopped by user.</Description>
    <StartTime>2023-06-05 14:11:11</StartTime>
    <Result>Information</Result>
    <Extension>
      <IconKey>d71b363451e24b4f944926c546ee9002</IconKey>
      <IsPlainTextNodeName>True</IsPlainTextNodeName>
    </Extension>
  </Data>
</ReportNode>
<Data>
    <Name>SMAG-0016 - Riwayat Pesan</Name>
    <Description />
    <StartTime>2023-06-05 14:11:10</StartTime>
    <Duration>1</Duration>
    <Result>Passed</Result>
    <Extension>
      <IconKey>fde8d33c0b6c460b90cf8818d6078b7e</IconKey>
      <IsPlainTextNodeName>True</IsPlainTextNodeName>
    </Extension>
    <Index>13</Index>
    <TestedApplications />
  </Data>
</ReportNode>
<ReportNode type="Iteration">
<ReportNode type="Step">
<Data>
    <Name>LoadFunctionLibrary</Name>
    <Description>LoadFunctionLibrary function passed</Description>
    <StartTime>2023-06-05 14:11:11</StartTime>
    <Result>Passed</Result>
    <Extension>
      <IconKey>6b3571f267314fd8800e5e9f08d7df52</IconKey>
      <IsPlainTextNodeName>True</IsPlainTextNodeName>
    </Extension>
    <DeviceInfo />
  </Data>
</ReportNode>
<ReportNode type="Step">
<Data>
    <Name>LoadFunctionLibrary</Name>
    <Description>LoadFunctionLibrary function passed</Description>
    <StartTime>2023-06-05 14:11:11</StartTime>
    <Result>Passed</Result>
    <Extension>
      <IconKey>6b3571f267314fd8800e5e9f08d7df52</IconKey>
      <IsPlainTextNodeName>True</IsPlainTextNodeName>
    </Extension>
    <DeviceInfo />
  </Data>
</ReportNode>
<ReportNode type="Step">
<Data>
    <Name>LoadFunctionLibrary</Name>
    <Description>LoadFunctionLibrary function passed</Description>
    <StartTime>2023-06-05 14:11:11</StartTime>
    <Result>Passed</Result>
    <Extension>
      <IconKey>6b3571f267314fd8800e5e9f08d7df52</IconKey>
      <IsPlainTextNodeName>True</IsPlainTextNodeName>
    </Extension>
    <DeviceInfo />
  </Data>
</ReportNode>
<ReportNode type="Step">
<Data>
    <Name>LoadFunctionLibrary</Name>
    <Description>LoadFunctionLibrary function passed</Description>
    <StartTime>2023-06-05 14:11:11</StartTime>
    <Result>Passed</Result>
    <Extension>
      <IconKey>6b3571f267314fd8800e5e9f08d7df52</IconKey>
      <IsPlainTextNodeName>True</IsPlainTextNodeName>
    </Extension>
    <DeviceInfo />
  </Data>
</ReportNode>
<ReportNode type="Step">
<Data>
    <Name>LoadFunctionLibrary</Name>
    <Description>LoadFunctionLibrary function passed</Description>
    <StartTime>2023-06-05 14:11:11</StartTime>
    <Result>Passed</Result>
    <Extension>
      <IconKey>6b3571f267314fd8800e5e9f08d7df52</IconKey>
      <IsPlainTextNodeName>True</IsPlainTextNodeName>
    </Extension>
    <DeviceInfo />
  </Data>
</ReportNode>
<ReportNode type="Step">
<Data>
    <Name>Stop action iteration replay</Name>
    <Description>Run stopped by user.</Description>
    <StartTime>2023-06-05 14:11:12</StartTime>
    <Result>Information</Result>
    <Extension>
      <IconKey>d71b363451e24b4f944926c546ee9002</IconKey>
      <IsPlainTextNodeName>True</IsPlainTextNodeName>
    </Extension>
  </Data>
</ReportNode>
<Data>
    <Name>SMAG-0016 - Riwayat Pesan</Name>
    <Description />
    <StartTime>2023-06-05 14:11:11</StartTime>
    <Duration>1</Duration>
    <Result>Passed</Result>
    <Extension>
      <IconKey>fde8d33c0b6c460b90cf8818d6078b7e</IconKey>
      <IsPlainTextNodeName>True</IsPlainTextNodeName>
    </Extension>
    <Index>14</Index>
    <TestedApplications />
  </Data>
</ReportNode>
<ReportNode type="Iteration">
<ReportNode type="Step">
<Data>
    <Name>LoadFunctionLibrary</Name>
    <Description>LoadFunctionLibrary function passed</Description>
    <StartTime>2023-06-05 14:11:12</StartTime>
    <Result>Passed</Result>
    <Extension>
      <IconKey>6b3571f267314fd8800e5e9f08d7df52</IconKey>
      <IsPlainTextNodeName>True</IsPlainTextNodeName>
    </Extension>
    <DeviceInfo />
  </Data>
</ReportNode>
<ReportNode type="Step">
<Data>
    <Name>LoadFunctionLibrary</Name>
    <Description>LoadFunctionLibrary function passed</Description>
    <StartTime>2023-06-05 14:11:12</StartTime>
    <Result>Passed</Result>
    <Extension>
      <IconKey>6b3571f267314fd8800e5e9f08d7df52</IconKey>
      <IsPlainTextNodeName>True</IsPlainTextNodeName>
    </Extension>
    <DeviceInfo />
  </Data>
</ReportNode>
<ReportNode type="Step">
<Data>
    <Name>LoadFunctionLibrary</Name>
    <Description>LoadFunctionLibrary function passed</Description>
    <StartTime>2023-06-05 14:11:12</StartTime>
    <Result>Passed</Result>
    <Extension>
      <IconKey>6b3571f267314fd8800e5e9f08d7df52</IconKey>
      <IsPlainTextNodeName>True</IsPlainTextNodeName>
    </Extension>
    <DeviceInfo />
  </Data>
</ReportNode>
<ReportNode type="Step">
<Data>
    <Name>LoadFunctionLibrary</Name>
    <Description>LoadFunctionLibrary function passed</Description>
    <StartTime>2023-06-05 14:11:12</StartTime>
    <Result>Passed</Result>
    <Extension>
      <IconKey>6b3571f267314fd8800e5e9f08d7df52</IconKey>
      <IsPlainTextNodeName>True</IsPlainTextNodeName>
    </Extension>
    <DeviceInfo />
  </Data>
</ReportNode>
<ReportNode type="Step">
<Data>
    <Name>LoadFunctionLibrary</Name>
    <Description>LoadFunctionLibrary function passed</Description>
    <StartTime>2023-06-05 14:11:12</StartTime>
    <Result>Passed</Result>
    <Extension>
      <IconKey>6b3571f267314fd8800e5e9f08d7df52</IconKey>
      <IsPlainTextNodeName>True</IsPlainTextNodeName>
    </Extension>
    <DeviceInfo />
  </Data>
</ReportNode>
<ReportNode type="Step">
<Data>
    <Name>Stop action iteration replay</Name>
    <Description>Run stopped by user.</Description>
    <StartTime>2023-06-05 14:11:12</StartTime>
    <Result>Information</Result>
    <Extension>
      <IconKey>d71b363451e24b4f944926c546ee9002</IconKey>
      <IsPlainTextNodeName>True</IsPlainTextNodeName>
    </Extension>
  </Data>
</ReportNode>
<Data>
    <Name>SMAG-0016 - Riwayat Pesan</Name>
    <Description />
    <StartTime>2023-06-05 14:11:12</StartTime>
    <Duration>0</Duration>
    <Result>Passed</Result>
    <Extension>
      <IconKey>fde8d33c0b6c460b90cf8818d6078b7e</IconKey>
      <IsPlainTextNodeName>True</IsPlainTextNodeName>
    </Extension>
    <Index>15</Index>
    <TestedApplications />
  </Data>
</ReportNode>
<ReportNode type="Iteration">
<ReportNode type="Step">
<Data>
    <Name>LoadFunctionLibrary</Name>
    <Description>LoadFunctionLibrary function passed</Description>
    <StartTime>2023-06-05 14:11:12</StartTime>
    <Result>Passed</Result>
    <Extension>
      <IconKey>6b3571f267314fd8800e5e9f08d7df52</IconKey>
      <IsPlainTextNodeName>True</IsPlainTextNodeName>
    </Extension>
    <DeviceInfo />
  </Data>
</ReportNode>
<ReportNode type="Step">
<Data>
    <Name>LoadFunctionLibrary</Name>
    <Description>LoadFunctionLibrary function passed</Description>
    <StartTime>2023-06-05 14:11:12</StartTime>
    <Result>Passed</Result>
    <Extension>
      <IconKey>6b3571f267314fd8800e5e9f08d7df52</IconKey>
      <IsPlainTextNodeName>True</IsPlainTextNodeName>
    </Extension>
    <DeviceInfo />
  </Data>
</ReportNode>
<ReportNode type="Step">
<Data>
    <Name>LoadFunctionLibrary</Name>
    <Description>LoadFunctionLibrary function passed</Description>
    <StartTime>2023-06-05 14:11:12</StartTime>
    <Result>Passed</Result>
    <Extension>
      <IconKey>6b3571f267314fd8800e5e9f08d7df52</IconKey>
      <IsPlainTextNodeName>True</IsPlainTextNodeName>
    </Extension>
    <DeviceInfo />
  </Data>
</ReportNode>
<ReportNode type="Step">
<Data>
    <Name>LoadFunctionLibrary</Name>
    <Description>LoadFunctionLibrary function passed</Description>
    <StartTime>2023-06-05 14:11:12</StartTime>
    <Result>Passed</Result>
    <Extension>
      <IconKey>6b3571f267314fd8800e5e9f08d7df52</IconKey>
      <IsPlainTextNodeName>True</IsPlainTextNodeName>
    </Extension>
    <DeviceInfo />
  </Data>
</ReportNode>
<ReportNode type="Step">
<Data>
    <Name>LoadFunctionLibrary</Name>
    <Description>LoadFunctionLibrary function passed</Description>
    <StartTime>2023-06-05 14:11:12</StartTime>
    <Result>Passed</Result>
    <Extension>
      <IconKey>6b3571f267314fd8800e5e9f08d7df52</IconKey>
      <IsPlainTextNodeName>True</IsPlainTextNodeName>
    </Extension>
    <DeviceInfo />
  </Data>
</ReportNode>
<ReportNode type="Step">
<Data>
    <Name>Stop action iteration replay</Name>
    <Description>Run stopped by user.</Description>
    <StartTime>2023-06-05 14:11:13</StartTime>
    <Result>Information</Result>
    <Extension>
      <IconKey>d71b363451e24b4f944926c546ee9002</IconKey>
      <IsPlainTextNodeName>True</IsPlainTextNodeName>
    </Extension>
  </Data>
</ReportNode>
<Data>
    <Name>SMAG-0016 - Riwayat Pesan</Name>
    <Description />
    <StartTime>2023-06-05 14:11:12</StartTime>
    <Duration>1</Duration>
    <Result>Passed</Result>
    <Extension>
      <IconKey>fde8d33c0b6c460b90cf8818d6078b7e</IconKey>
      <IsPlainTextNodeName>True</IsPlainTextNodeName>
    </Extension>
    <Index>16</Index>
    <TestedApplications />
  </Data>
</ReportNode>
<ReportNode type="Iteration">
<ReportNode type="Step">
<Data>
    <Name>LoadFunctionLibrary</Name>
    <Description>LoadFunctionLibrary function passed</Description>
    <StartTime>2023-06-05 14:11:13</StartTime>
    <Result>Passed</Result>
    <Extension>
      <IconKey>6b3571f267314fd8800e5e9f08d7df52</IconKey>
      <IsPlainTextNodeName>True</IsPlainTextNodeName>
    </Extension>
    <DeviceInfo />
  </Data>
</ReportNode>
<ReportNode type="Step">
<Data>
    <Name>LoadFunctionLibrary</Name>
    <Description>LoadFunctionLibrary function passed</Description>
    <StartTime>2023-06-05 14:11:13</StartTime>
    <Result>Passed</Result>
    <Extension>
      <IconKey>6b3571f267314fd8800e5e9f08d7df52</IconKey>
      <IsPlainTextNodeName>True</IsPlainTextNodeName>
    </Extension>
    <DeviceInfo />
  </Data>
</ReportNode>
<ReportNode type="Step">
<Data>
    <Name>LoadFunctionLibrary</Name>
    <Description>LoadFunctionLibrary function passed</Description>
    <StartTime>2023-06-05 14:11:13</StartTime>
    <Result>Passed</Result>
    <Extension>
      <IconKey>6b3571f267314fd8800e5e9f08d7df52</IconKey>
      <IsPlainTextNodeName>True</IsPlainTextNodeName>
    </Extension>
    <DeviceInfo />
  </Data>
</ReportNode>
<ReportNode type="Step">
<Data>
    <Name>LoadFunctionLibrary</Name>
    <Description>LoadFunctionLibrary function passed</Description>
    <StartTime>2023-06-05 14:11:13</StartTime>
    <Result>Passed</Result>
    <Extension>
      <IconKey>6b3571f267314fd8800e5e9f08d7df52</IconKey>
      <IsPlainTextNodeName>True</IsPlainTextNodeName>
    </Extension>
    <DeviceInfo />
  </Data>
</ReportNode>
<ReportNode type="Step">
<Data>
    <Name>LoadFunctionLibrary</Name>
    <Description>LoadFunctionLibrary function passed</Description>
    <StartTime>2023-06-05 14:11:13</StartTime>
    <Result>Passed</Result>
    <Extension>
      <IconKey>6b3571f267314fd8800e5e9f08d7df52</IconKey>
      <IsPlainTextNodeName>True</IsPlainTextNodeName>
    </Extension>
    <DeviceInfo />
  </Data>
</ReportNode>
<ReportNode type="Step">
<Data>
    <Name>Stop action iteration replay</Name>
    <Description>Run stopped by user.</Description>
    <StartTime>2023-06-05 14:11:13</StartTime>
    <Result>Information</Result>
    <Extension>
      <IconKey>d71b363451e24b4f944926c546ee9002</IconKey>
      <IsPlainTextNodeName>True</IsPlainTextNodeName>
    </Extension>
  </Data>
</ReportNode>
<Data>
    <Name>SMAG-0016 - Riwayat Pesan</Name>
    <Description />
    <StartTime>2023-06-05 14:11:13</StartTime>
    <Duration>0</Duration>
    <Result>Passed</Result>
    <Extension>
      <IconKey>fde8d33c0b6c460b90cf8818d6078b7e</IconKey>
      <IsPlainTextNodeName>True</IsPlainTextNodeName>
    </Extension>
    <Index>17</Index>
    <TestedApplications />
  </Data>
</ReportNode>
<ReportNode type="Iteration">
<ReportNode type="Step">
<Data>
    <Name>LoadFunctionLibrary</Name>
    <Description>LoadFunctionLibrary function passed</Description>
    <StartTime>2023-06-05 14:11:13</StartTime>
    <Result>Passed</Result>
    <Extension>
      <IconKey>6b3571f267314fd8800e5e9f08d7df52</IconKey>
      <IsPlainTextNodeName>True</IsPlainTextNodeName>
    </Extension>
    <DeviceInfo />
  </Data>
</ReportNode>
<ReportNode type="Step">
<Data>
    <Name>LoadFunctionLibrary</Name>
    <Description>LoadFunctionLibrary function passed</Description>
    <StartTime>2023-06-05 14:11:14</StartTime>
    <Result>Passed</Result>
    <Extension>
      <IconKey>6b3571f267314fd8800e5e9f08d7df52</IconKey>
      <IsPlainTextNodeName>True</IsPlainTextNodeName>
    </Extension>
    <DeviceInfo />
  </Data>
</ReportNode>
<ReportNode type="Step">
<Data>
    <Name>LoadFunctionLibrary</Name>
    <Description>LoadFunctionLibrary function passed</Description>
    <StartTime>2023-06-05 14:11:14</StartTime>
    <Result>Passed</Result>
    <Extension>
      <IconKey>6b3571f267314fd8800e5e9f08d7df52</IconKey>
      <IsPlainTextNodeName>True</IsPlainTextNodeName>
    </Extension>
    <DeviceInfo />
  </Data>
</ReportNode>
<ReportNode type="Step">
<Data>
    <Name>LoadFunctionLibrary</Name>
    <Description>LoadFunctionLibrary function passed</Description>
    <StartTime>2023-06-05 14:11:14</StartTime>
    <Result>Passed</Result>
    <Extension>
      <IconKey>6b3571f267314fd8800e5e9f08d7df52</IconKey>
      <IsPlainTextNodeName>True</IsPlainTextNodeName>
    </Extension>
    <DeviceInfo />
  </Data>
</ReportNode>
<ReportNode type="Step">
<Data>
    <Name>LoadFunctionLibrary</Name>
    <Description>LoadFunctionLibrary function passed</Description>
    <StartTime>2023-06-05 14:11:14</StartTime>
    <Result>Passed</Result>
    <Extension>
      <IconKey>6b3571f267314fd8800e5e9f08d7df52</IconKey>
      <IsPlainTextNodeName>True</IsPlainTextNodeName>
    </Extension>
    <DeviceInfo />
  </Data>
</ReportNode>
<ReportNode type="Step">
<Data>
    <Name>Stop action iteration replay</Name>
    <Description>Run stopped by user.</Description>
    <StartTime>2023-06-05 14:11:14</StartTime>
    <Result>Information</Result>
    <Extension>
      <IconKey>d71b363451e24b4f944926c546ee9002</IconKey>
      <IsPlainTextNodeName>True</IsPlainTextNodeName>
    </Extension>
  </Data>
</ReportNode>
<Data>
    <Name>SMAG-0016 - Riwayat Pesan</Name>
    <Description />
    <StartTime>2023-06-05 14:11:13</StartTime>
    <Duration>1</Duration>
    <Result>Passed</Result>
    <Extension>
      <IconKey>fde8d33c0b6c460b90cf8818d6078b7e</IconKey>
      <IsPlainTextNodeName>True</IsPlainTextNodeName>
    </Extension>
    <Index>18</Index>
    <TestedApplications />
  </Data>
</ReportNode>
<ReportNode type="Iteration">
<ReportNode type="Step">
<Data>
    <Name>LoadFunctionLibrary</Name>
    <Description>LoadFunctionLibrary function passed</Description>
    <StartTime>2023-06-05 14:11:14</StartTime>
    <Result>Passed</Result>
    <Extension>
      <IconKey>6b3571f267314fd8800e5e9f08d7df52</IconKey>
      <IsPlainTextNodeName>True</IsPlainTextNodeName>
    </Extension>
    <DeviceInfo />
  </Data>
</ReportNode>
<ReportNode type="Step">
<Data>
    <Name>LoadFunctionLibrary</Name>
    <Description>LoadFunctionLibrary function passed</Description>
    <StartTime>2023-06-05 14:11:14</StartTime>
    <Result>Passed</Result>
    <Extension>
      <IconKey>6b3571f267314fd8800e5e9f08d7df52</IconKey>
      <IsPlainTextNodeName>True</IsPlainTextNodeName>
    </Extension>
    <DeviceInfo />
  </Data>
</ReportNode>
<ReportNode type="Step">
<Data>
    <Name>LoadFunctionLibrary</Name>
    <Description>LoadFunctionLibrary function passed</Description>
    <StartTime>2023-06-05 14:11:14</StartTime>
    <Result>Passed</Result>
    <Extension>
      <IconKey>6b3571f267314fd8800e5e9f08d7df52</IconKey>
      <IsPlainTextNodeName>True</IsPlainTextNodeName>
    </Extension>
    <DeviceInfo />
  </Data>
</ReportNode>
<ReportNode type="Step">
<Data>
    <Name>LoadFunctionLibrary</Name>
    <Description>LoadFunctionLibrary function passed</Description>
    <StartTime>2023-06-05 14:11:14</StartTime>
    <Result>Passed</Result>
    <Extension>
      <IconKey>6b3571f267314fd8800e5e9f08d7df52</IconKey>
      <IsPlainTextNodeName>True</IsPlainTextNodeName>
    </Extension>
    <DeviceInfo />
  </Data>
</ReportNode>
<ReportNode type="Step">
<Data>
    <Name>LoadFunctionLibrary</Name>
    <Description>LoadFunctionLibrary function passed</Description>
    <StartTime>2023-06-05 14:11:14</StartTime>
    <Result>Passed</Result>
    <Extension>
      <IconKey>6b3571f267314fd8800e5e9f08d7df52</IconKey>
      <IsPlainTextNodeName>True</IsPlainTextNodeName>
    </Extension>
    <DeviceInfo />
  </Data>
</ReportNode>
<ReportNode type="Step">
<Data>
    <Name>Stop action iteration replay</Name>
    <Description>Run stopped by user.</Description>
    <StartTime>2023-06-05 14:11:14</StartTime>
    <Result>Information</Result>
    <Extension>
      <IconKey>d71b363451e24b4f944926c546ee9002</IconKey>
      <IsPlainTextNodeName>True</IsPlainTextNodeName>
    </Extension>
  </Data>
</ReportNode>
<Data>
    <Name>SMAG-0016 - Riwayat Pesan</Name>
    <Description />
    <StartTime>2023-06-05 14:11:14</StartTime>
    <Duration>0</Duration>
    <Result>Passed</Result>
    <Extension>
      <IconKey>fde8d33c0b6c460b90cf8818d6078b7e</IconKey>
      <IsPlainTextNodeName>True</IsPlainTextNodeName>
    </Extension>
    <Index>19</Index>
    <TestedApplications />
  </Data>
</ReportNode>
<ReportNode type="Iteration">
<ReportNode type="Step">
<Data>
    <Name>LoadFunctionLibrary</Name>
    <Description>LoadFunctionLibrary function passed</Description>
    <StartTime>2023-06-05 14:11:15</StartTime>
    <Result>Passed</Result>
    <Extension>
      <IconKey>6b3571f267314fd8800e5e9f08d7df52</IconKey>
      <IsPlainTextNodeName>True</IsPlainTextNodeName>
    </Extension>
    <DeviceInfo />
  </Data>
</ReportNode>
<ReportNode type="Step">
<Data>
    <Name>LoadFunctionLibrary</Name>
    <Description>LoadFunctionLibrary function passed</Description>
    <StartTime>2023-06-05 14:11:15</StartTime>
    <Result>Passed</Result>
    <Extension>
      <IconKey>6b3571f267314fd8800e5e9f08d7df52</IconKey>
      <IsPlainTextNodeName>True</IsPlainTextNodeName>
    </Extension>
    <DeviceInfo />
  </Data>
</ReportNode>
<ReportNode type="Step">
<Data>
    <Name>LoadFunctionLibrary</Name>
    <Description>LoadFunctionLibrary function passed</Description>
    <StartTime>2023-06-05 14:11:15</StartTime>
    <Result>Passed</Result>
    <Extension>
      <IconKey>6b3571f267314fd8800e5e9f08d7df52</IconKey>
      <IsPlainTextNodeName>True</IsPlainTextNodeName>
    </Extension>
    <DeviceInfo />
  </Data>
</ReportNode>
<ReportNode type="Step">
<Data>
    <Name>LoadFunctionLibrary</Name>
    <Description>LoadFunctionLibrary function passed</Description>
    <StartTime>2023-06-05 14:11:15</StartTime>
    <Result>Passed</Result>
    <Extension>
      <IconKey>6b3571f267314fd8800e5e9f08d7df52</IconKey>
      <IsPlainTextNodeName>True</IsPlainTextNodeName>
    </Extension>
    <DeviceInfo />
  </Data>
</ReportNode>
<ReportNode type="Step">
<Data>
    <Name>LoadFunctionLibrary</Name>
    <Description>LoadFunctionLibrary function passed</Description>
    <StartTime>2023-06-05 14:11:15</StartTime>
    <Result>Passed</Result>
    <Extension>
      <IconKey>6b3571f267314fd8800e5e9f08d7df52</IconKey>
      <IsPlainTextNodeName>True</IsPlainTextNodeName>
    </Extension>
    <DeviceInfo />
  </Data>
</ReportNode>
<ReportNode type="Step">
<Data>
    <Name>Stop action iteration replay</Name>
    <Description>Run stopped by user.</Description>
    <StartTime>2023-06-05 14:11:15</StartTime>
    <Result>Information</Result>
    <Extension>
      <IconKey>d71b363451e24b4f944926c546ee9002</IconKey>
      <IsPlainTextNodeName>True</IsPlainTextNodeName>
    </Extension>
  </Data>
</ReportNode>
<Data>
    <Name>SMAG-0016 - Riwayat Pesan</Name>
    <Description />
    <StartTime>2023-06-05 14:11:14</StartTime>
    <Duration>1</Duration>
    <Result>Passed</Result>
    <Extension>
      <IconKey>fde8d33c0b6c460b90cf8818d6078b7e</IconKey>
      <IsPlainTextNodeName>True</IsPlainTextNodeName>
    </Extension>
    <Index>20</Index>
    <TestedApplications />
  </Data>
</ReportNode>
<ReportNode type="Iteration">
<ReportNode type="Step">
<Data>
    <Name>LoadFunctionLibrary</Name>
    <Description>LoadFunctionLibrary function passed</Description>
    <StartTime>2023-06-05 14:11:15</StartTime>
    <Result>Passed</Result>
    <Extension>
      <IconKey>6b3571f267314fd8800e5e9f08d7df52</IconKey>
      <IsPlainTextNodeName>True</IsPlainTextNodeName>
    </Extension>
    <DeviceInfo />
  </Data>
</ReportNode>
<ReportNode type="Step">
<Data>
    <Name>LoadFunctionLibrary</Name>
    <Description>LoadFunctionLibrary function passed</Description>
    <StartTime>2023-06-05 14:11:15</StartTime>
    <Result>Passed</Result>
    <Extension>
      <IconKey>6b3571f267314fd8800e5e9f08d7df52</IconKey>
      <IsPlainTextNodeName>True</IsPlainTextNodeName>
    </Extension>
    <DeviceInfo />
  </Data>
</ReportNode>
<ReportNode type="Step">
<Data>
    <Name>LoadFunctionLibrary</Name>
    <Description>LoadFunctionLibrary function passed</Description>
    <StartTime>2023-06-05 14:11:15</StartTime>
    <Result>Passed</Result>
    <Extension>
      <IconKey>6b3571f267314fd8800e5e9f08d7df52</IconKey>
      <IsPlainTextNodeName>True</IsPlainTextNodeName>
    </Extension>
    <DeviceInfo />
  </Data>
</ReportNode>
<ReportNode type="Step">
<Data>
    <Name>LoadFunctionLibrary</Name>
    <Description>LoadFunctionLibrary function passed</Description>
    <StartTime>2023-06-05 14:11:15</StartTime>
    <Result>Passed</Result>
    <Extension>
      <IconKey>6b3571f267314fd8800e5e9f08d7df52</IconKey>
      <IsPlainTextNodeName>True</IsPlainTextNodeName>
    </Extension>
    <DeviceInfo />
  </Data>
</ReportNode>
<ReportNode type="Step">
<Data>
    <Name>LoadFunctionLibrary</Name>
    <Description>LoadFunctionLibrary function passed</Description>
    <StartTime>2023-06-05 14:11:15</StartTime>
    <Result>Passed</Result>
    <Extension>
      <IconKey>6b3571f267314fd8800e5e9f08d7df52</IconKey>
      <IsPlainTextNodeName>True</IsPlainTextNodeName>
    </Extension>
    <DeviceInfo />
  </Data>
</ReportNode>
<ReportNode type="Step">
<Data>
    <Name>Stop action iteration replay</Name>
    <Description>Run stopped by user.</Description>
    <StartTime>2023-06-05 14:11:16</StartTime>
    <Result>Information</Result>
    <Extension>
      <IconKey>d71b363451e24b4f944926c546ee9002</IconKey>
      <IsPlainTextNodeName>True</IsPlainTextNodeName>
    </Extension>
  </Data>
</ReportNode>
<Data>
    <Name>SMAG-0016 - Riwayat Pesan</Name>
    <Description />
    <StartTime>2023-06-05 14:11:15</StartTime>
    <Duration>1</Duration>
    <Result>Passed</Result>
    <Extension>
      <IconKey>fde8d33c0b6c460b90cf8818d6078b7e</IconKey>
      <IsPlainTextNodeName>True</IsPlainTextNodeName>
    </Extension>
    <Index>21</Index>
    <TestedApplications />
  </Data>
</ReportNode>
<ReportNode type="Iteration">
<ReportNode type="Step">
<Data>
    <Name>LoadFunctionLibrary</Name>
    <Description>LoadFunctionLibrary function passed</Description>
    <StartTime>2023-06-05 14:11:16</StartTime>
    <Result>Passed</Result>
    <Extension>
      <IconKey>6b3571f267314fd8800e5e9f08d7df52</IconKey>
      <IsPlainTextNodeName>True</IsPlainTextNodeName>
    </Extension>
    <DeviceInfo />
  </Data>
</ReportNode>
<ReportNode type="Step">
<Data>
    <Name>LoadFunctionLibrary</Name>
    <Description>LoadFunctionLibrary function passed</Description>
    <StartTime>2023-06-05 14:11:16</StartTime>
    <Result>Passed</Result>
    <Extension>
      <IconKey>6b3571f267314fd8800e5e9f08d7df52</IconKey>
      <IsPlainTextNodeName>True</IsPlainTextNodeName>
    </Extension>
    <DeviceInfo />
  </Data>
</ReportNode>
<ReportNode type="Step">
<Data>
    <Name>LoadFunctionLibrary</Name>
    <Description>LoadFunctionLibrary function passed</Description>
    <StartTime>2023-06-05 14:11:16</StartTime>
    <Result>Passed</Result>
    <Extension>
      <IconKey>6b3571f267314fd8800e5e9f08d7df52</IconKey>
      <IsPlainTextNodeName>True</IsPlainTextNodeName>
    </Extension>
    <DeviceInfo />
  </Data>
</ReportNode>
<ReportNode type="Step">
<Data>
    <Name>LoadFunctionLibrary</Name>
    <Description>LoadFunctionLibrary function passed</Description>
    <StartTime>2023-06-05 14:11:16</StartTime>
    <Result>Passed</Result>
    <Extension>
      <IconKey>6b3571f267314fd8800e5e9f08d7df52</IconKey>
      <IsPlainTextNodeName>True</IsPlainTextNodeName>
    </Extension>
    <DeviceInfo />
  </Data>
</ReportNode>
<ReportNode type="Step">
<Data>
    <Name>LoadFunctionLibrary</Name>
    <Description>LoadFunctionLibrary function passed</Description>
    <StartTime>2023-06-05 14:11:16</StartTime>
    <Result>Passed</Result>
    <Extension>
      <IconKey>6b3571f267314fd8800e5e9f08d7df52</IconKey>
      <IsPlainTextNodeName>True</IsPlainTextNodeName>
    </Extension>
    <DeviceInfo />
  </Data>
</ReportNode>
<ReportNode type="Step">
<Data>
    <Name>Stop action iteration replay</Name>
    <Description>Run stopped by user.</Description>
    <StartTime>2023-06-05 14:11:16</StartTime>
    <Result>Information</Result>
    <Extension>
      <IconKey>d71b363451e24b4f944926c546ee9002</IconKey>
      <IsPlainTextNodeName>True</IsPlainTextNodeName>
    </Extension>
  </Data>
</ReportNode>
<Data>
    <Name>SMAG-0016 - Riwayat Pesan</Name>
    <Description />
    <StartTime>2023-06-05 14:11:16</StartTime>
    <Duration>0</Duration>
    <Result>Passed</Result>
    <Extension>
      <IconKey>fde8d33c0b6c460b90cf8818d6078b7e</IconKey>
      <IsPlainTextNodeName>True</IsPlainTextNodeName>
    </Extension>
    <Index>22</Index>
    <TestedApplications />
  </Data>
</ReportNode>
<ReportNode type="Iteration">
<ReportNode type="Step">
<Data>
    <Name>LoadFunctionLibrary</Name>
    <Description>LoadFunctionLibrary function passed</Description>
    <StartTime>2023-06-05 14:11:16</StartTime>
    <Result>Passed</Result>
    <Extension>
      <IconKey>6b3571f267314fd8800e5e9f08d7df52</IconKey>
      <IsPlainTextNodeName>True</IsPlainTextNodeName>
    </Extension>
    <DeviceInfo />
  </Data>
</ReportNode>
<ReportNode type="Step">
<Data>
    <Name>LoadFunctionLibrary</Name>
    <Description>LoadFunctionLibrary function passed</Description>
    <StartTime>2023-06-05 14:11:16</StartTime>
    <Result>Passed</Result>
    <Extension>
      <IconKey>6b3571f267314fd8800e5e9f08d7df52</IconKey>
      <IsPlainTextNodeName>True</IsPlainTextNodeName>
    </Extension>
    <DeviceInfo />
  </Data>
</ReportNode>
<ReportNode type="Step">
<Data>
    <Name>LoadFunctionLibrary</Name>
    <Description>LoadFunctionLibrary function passed</Description>
    <StartTime>2023-06-05 14:11:16</StartTime>
    <Result>Passed</Result>
    <Extension>
      <IconKey>6b3571f267314fd8800e5e9f08d7df52</IconKey>
      <IsPlainTextNodeName>True</IsPlainTextNodeName>
    </Extension>
    <DeviceInfo />
  </Data>
</ReportNode>
<ReportNode type="Step">
<Data>
    <Name>LoadFunctionLibrary</Name>
    <Description>LoadFunctionLibrary function passed</Description>
    <StartTime>2023-06-05 14:11:16</StartTime>
    <Result>Passed</Result>
    <Extension>
      <IconKey>6b3571f267314fd8800e5e9f08d7df52</IconKey>
      <IsPlainTextNodeName>True</IsPlainTextNodeName>
    </Extension>
    <DeviceInfo />
  </Data>
</ReportNode>
<ReportNode type="Step">
<Data>
    <Name>LoadFunctionLibrary</Name>
    <Description>LoadFunctionLibrary function passed</Description>
    <StartTime>2023-06-05 14:11:17</StartTime>
    <Result>Passed</Result>
    <Extension>
      <IconKey>6b3571f267314fd8800e5e9f08d7df52</IconKey>
      <IsPlainTextNodeName>True</IsPlainTextNodeName>
    </Extension>
    <DeviceInfo />
  </Data>
</ReportNode>
<ReportNode type="Step">
<Data>
    <Name>Stop action iteration replay</Name>
    <Description>Run stopped by user.</Description>
    <StartTime>2023-06-05 14:11:24</StartTime>
    <Result>Information</Result>
    <Extension>
      <IconKey>d71b363451e24b4f944926c546ee9002</IconKey>
      <IsPlainTextNodeName>True</IsPlainTextNodeName>
    </Extension>
  </Data>
</ReportNode>
<Data>
    <Name>SMAG-0016 - Riwayat Pesan</Name>
    <Description />
    <StartTime>2023-06-05 14:11:16</StartTime>
    <Duration>8</Duration>
    <Result>Passed</Result>
    <Extension>
      <IconKey>fde8d33c0b6c460b90cf8818d6078b7e</IconKey>
      <IsPlainTextNodeName>True</IsPlainTextNodeName>
    </Extension>
    <Index>23</Index>
    <TestedApplications />
  </Data>
</ReportNode>
<Data>
    <Name>SMAG-0016 - Riwayat Pesan</Name>
    <Description />
    <StartTime>2023-06-05 14:07:48</StartTime>
    <Duration>216</Duration>
    <Result>Passed</Result>
    <InputParameters />
    <Extension>
      <IconKey>ca9932beafb44ee78a3768edc3888b02</IconKey>
      <IsPlainTextNodeName>True</IsPlainTextNodeName>
    </Extension>
  </Data>
</ReportNode>
<Data>
    <Name>Action0</Name>
    <Description />
    <StartTime>2023-06-05 14:07:48</StartTime>
    <Duration>216</Duration>
    <Result>Passed</Result>
    <Extension>
      <IconKey>fde8d33c0b6c460b90cf8818d6078b7e</IconKey>
      <IsPlainTextNodeName>True</IsPlainTextNodeName>
    </Extension>
    <Index>1</Index>
    <TestedApplications />
  </Data>
</ReportNode>
<Data>
    <Name>SMAG-0016_Riwayat_Pesan</Name>
    <ToolName>Micro Focus UFT One</ToolName>
    <ToolVersion>2021</ToolVersion>
    <ToolVersionStringLiteral>2021</ToolVersionStringLiteral>
    <Description />
    <StartTime>2023-06-05 14:07:45</StartTime>
    <Duration>219</Duration>
    <Result>Passed</Result>
    <InputParameters />
    <Extension>
      <IconKey>fc16a479bbf14c63a849b925fae5e7c0</IconKey>
      <IsPlainTextNodeName>True</IsPlainTextNodeName>
    </Extension>
    <Environment>
      <Timezone>+07:00:00</Timezone>
      <Locale>English (Indonesia)</Locale>
      <User>asus</User>
      <CpuInfo>11th Gen Intel(R) Core(TM) i5-11300H @ 3.10GHz</CpuInfo>
      <NumberOfCores>8</NumberOfCores>
      <TotalMemory>7871</TotalMemory>
      <HostName>LAPTOP-JDUEI4CK</HostName>
      <OSInfo>Windows 11 22H2 (x64)</OSInfo>
    </Environment>
    <TestedApplications />
    <Links>
      <Link type="DataTable" reference="Default.xlsx" displayname="Default Data Table" />
    </Links>
  </Data>
</ReportNode>
<GeneralInfo>
    <ResultName>Res14</ResultName>
    <RunStartTime>2023-06-05 14:07:45</RunStartTime>
    <Timezone>+07:00:00</Timezone>
    <OrchestrationToolName>Micro Focus UFT One</OrchestrationToolName>
    <OrchestrationToolVersion>2021</OrchestrationToolVersion>
    <OrchestrationToolVersionStringLiteral>2021</OrchestrationToolVersionStringLiteral>
  </GeneralInfo>
</Results>