<?xml version="1.0"?>
<Results version="1.0">
<ReportNode type="testrun">
<ReportNode type="Iteration">
<ReportNode type="Action">
<ReportNode type="Iteration">
<ReportNode type="Step">
<Data>
    <Name>LoadFunctionLibrary</Name>
    <Description>LoadFunctionLibrary function passed</Description>
    <StartTime>2023-01-24 15:16:35</StartTime>
    <Result>Passed</Result>
    <Extension>
      <IconKey>2f6f48721088477aa1854766bb4294d5</IconKey>
      <IsPlainTextNodeName>True</IsPlainTextNodeName>
    </Extension>
    <DeviceInfo />
  </Data>
</ReportNode>
<ReportNode type="Step">
<Data>
    <Name>LoadFunctionLibrary</Name>
    <Description>LoadFunctionLibrary function passed</Description>
    <StartTime>2023-01-24 15:16:35</StartTime>
    <Result>Passed</Result>
    <Extension>
      <IconKey>2f6f48721088477aa1854766bb4294d5</IconKey>
      <IsPlainTextNodeName>True</IsPlainTextNodeName>
    </Extension>
    <DeviceInfo />
  </Data>
</ReportNode>
<ReportNode type="Step">
<Data>
    <Name>LoadFunctionLibrary</Name>
    <Description>LoadFunctionLibrary function passed</Description>
    <StartTime>2023-01-24 15:16:35</StartTime>
    <Result>Passed</Result>
    <Extension>
      <IconKey>2f6f48721088477aa1854766bb4294d5</IconKey>
      <IsPlainTextNodeName>True</IsPlainTextNodeName>
    </Extension>
    <DeviceInfo />
  </Data>
</ReportNode>
<ReportNode type="Step">
<Data>
    <Name>LoadFunctionLibrary</Name>
    <Description>LoadFunctionLibrary function passed</Description>
    <StartTime>2023-01-24 15:16:35</StartTime>
    <Result>Passed</Result>
    <Extension>
      <IconKey>2f6f48721088477aa1854766bb4294d5</IconKey>
      <IsPlainTextNodeName>True</IsPlainTextNodeName>
    </Extension>
    <DeviceInfo />
  </Data>
</ReportNode>
<ReportNode type="Step">
<Data>
    <Name>LoadFunctionLibrary</Name>
    <Description>LoadFunctionLibrary function passed</Description>
    <StartTime>2023-01-24 15:16:36</StartTime>
    <Result>Passed</Result>
    <Extension>
      <IconKey>2f6f48721088477aa1854766bb4294d5</IconKey>
      <IsPlainTextNodeName>True</IsPlainTextNodeName>
    </Extension>
    <DeviceInfo />
  </Data>
</ReportNode>
<ReportNode type="Context">
<ReportNode type="Context">
<ReportNode type="Step">
<Data>
    <Name>Bayar dan Beli.Tap</Name>
    <Description />
    <StartTime>2023-01-24 15:16:57</StartTime>
    <Result>Done</Result>
    <Extension>
      <TestObject>
        <Repository>C:\Users\1420\Desktop\Mobile Keagenan Android\Lib_Repo_Excel_Keagenan_Mobile\Repo_Keagenan_Mobile\RP_KeagenanMobile_TiketTransportasi.tsr</Repository>
        <Path>
          <Object>
            <Type>Device</Type>
            <Name><![CDATA[Device]]></Name>
          </Object>
          <Object>
            <Type>App</Type>
            <Name><![CDATA[BNI Agen46]]></Name>
          </Object>
          <Object>
            <Type>MobileObject</Type>
            <Name><![CDATA[Bayar dan Beli]]></Name>
          </Object>
        </Path>
        <Operation>Tap</Operation>
        <Properties>
          <Property>
            <Name><![CDATA[resourceid]]></Name>
            <Value><![CDATA[]]></Value>
          </Property>
          <Property>
            <Name><![CDATA[nativeclass]]></Name>
            <Value><![CDATA[android.widget.ImageView]]></Value>
          </Property>
          <Property>
            <Name><![CDATA[mcindex]]></Name>
            <Value><![CDATA[9]]></Value>
          </Property>
          <Property>
            <Name><![CDATA[class]]></Name>
            <Value><![CDATA[ImageView]]></Value>
          </Property>
          <Property>
            <Name><![CDATA[accessibilityid]]></Name>
            <Value><![CDATA[Bayar dan Beli]]></Value>
          </Property>
        </Properties>
      </TestObject>
      <IconKey>b887acea2f704ccf9f9d841494ccf91c</IconKey>
      <IsPlainTextNodeName>True</IsPlainTextNodeName>
    </Extension>
    <DeviceInfo />
  </Data>
</ReportNode>
<ReportNode type="Step">
<Data>
    <Name>Tiket Transportasi.Tap</Name>
    <Description />
    <StartTime>2023-01-24 15:17:12</StartTime>
    <Result>Done</Result>
    <Extension>
      <TestObject>
        <Repository>C:\Users\1420\Desktop\Mobile Keagenan Android\Lib_Repo_Excel_Keagenan_Mobile\Repo_Keagenan_Mobile\RP_KeagenanMobile_TiketTransportasi.tsr</Repository>
        <Path>
          <Object>
            <Type>Device</Type>
            <Name><![CDATA[Device]]></Name>
          </Object>
          <Object>
            <Type>App</Type>
            <Name><![CDATA[BNI Agen46]]></Name>
          </Object>
          <Object>
            <Type>MobileObject</Type>
            <Name><![CDATA[Tiket Transportasi]]></Name>
          </Object>
        </Path>
        <Operation>Tap</Operation>
        <Properties>
          <Property>
            <Name><![CDATA[resourceid]]></Name>
            <Value><![CDATA[]]></Value>
          </Property>
          <Property>
            <Name><![CDATA[nativeclass]]></Name>
            <Value><![CDATA[android.view.View]]></Value>
          </Property>
          <Property>
            <Name><![CDATA[mcindex]]></Name>
            <Value><![CDATA[28]]></Value>
          </Property>
          <Property>
            <Name><![CDATA[class]]></Name>
            <Value><![CDATA[View]]></Value>
          </Property>
          <Property>
            <Name><![CDATA[accessibilityid]]></Name>
            <Value><![CDATA[Tiket
Transportasi]]></Value>
          </Property>
        </Properties>
      </TestObject>
      <IconKey>b887acea2f704ccf9f9d841494ccf91c</IconKey>
      <IsPlainTextNodeName>True</IsPlainTextNodeName>
    </Extension>
    <DeviceInfo />
  </Data>
</ReportNode>
<ReportNode type="Step">
<Data>
    <Name>Tiket Penerbangan.Tap</Name>
    <Description />
    <StartTime>2023-01-24 15:17:26</StartTime>
    <Result>Done</Result>
    <Extension>
      <TestObject>
        <Repository>C:\Users\1420\Desktop\Mobile Keagenan Android\Lib_Repo_Excel_Keagenan_Mobile\Repo_Keagenan_Mobile\RP_KeagenanMobile_TiketTransportasi.tsr</Repository>
        <Path>
          <Object>
            <Type>Device</Type>
            <Name><![CDATA[Device]]></Name>
          </Object>
          <Object>
            <Type>App</Type>
            <Name><![CDATA[BNI Agen46]]></Name>
          </Object>
          <Object>
            <Type>MobileObject</Type>
            <Name><![CDATA[Tiket Penerbangan]]></Name>
          </Object>
        </Path>
        <Operation>Tap</Operation>
        <Properties>
          <Property>
            <Name><![CDATA[resourceid]]></Name>
            <Value><![CDATA[]]></Value>
          </Property>
          <Property>
            <Name><![CDATA[nativeclass]]></Name>
            <Value><![CDATA[android.widget.ImageView]]></Value>
          </Property>
          <Property>
            <Name><![CDATA[mcindex]]></Name>
            <Value><![CDATA[1]]></Value>
          </Property>
          <Property>
            <Name><![CDATA[class]]></Name>
            <Value><![CDATA[ImageView]]></Value>
          </Property>
          <Property>
            <Name><![CDATA[accessibilityid]]></Name>
            <Value><![CDATA[Tiket Penerbangan]]></Value>
          </Property>
        </Properties>
      </TestObject>
      <IconKey>b887acea2f704ccf9f9d841494ccf91c</IconKey>
      <IsPlainTextNodeName>True</IsPlainTextNodeName>
    </Extension>
    <DeviceInfo />
  </Data>
</ReportNode>
<ReportNode type="Step">
<Data>
    <Name>Maskapai.Tap</Name>
    <Description />
    <StartTime>2023-01-24 15:17:27</StartTime>
    <Result>Done</Result>
    <Extension>
      <TestObject>
        <Repository>C:\Users\1420\Desktop\Mobile Keagenan Android\Lib_Repo_Excel_Keagenan_Mobile\Repo_Keagenan_Mobile\RP_KeagenanMobile_TiketTransportasi.tsr</Repository>
        <Path>
          <Object>
            <Type>Device</Type>
            <Name><![CDATA[Device]]></Name>
          </Object>
          <Object>
            <Type>App</Type>
            <Name><![CDATA[BNI Agen46]]></Name>
          </Object>
          <Object>
            <Type>MobileObject</Type>
            <Name><![CDATA[Maskapai]]></Name>
          </Object>
        </Path>
        <Operation>Tap</Operation>
        <Properties>
          <Property>
            <Name><![CDATA[text]]></Name>
            <Value><![CDATA[Maskapai]]></Value>
          </Property>
          <Property>
            <Name><![CDATA[resourceid]]></Name>
            <Value><![CDATA[]]></Value>
          </Property>
          <Property>
            <Name><![CDATA[nativeclass]]></Name>
            <Value><![CDATA[android.view.View]]></Value>
          </Property>
          <Property>
            <Name><![CDATA[mcindex]]></Name>
            <Value><![CDATA[13]]></Value>
          </Property>
          <Property>
            <Name><![CDATA[class]]></Name>
            <Value><![CDATA[View]]></Value>
          </Property>
        </Properties>
      </TestObject>
      <IconKey>b887acea2f704ccf9f9d841494ccf91c</IconKey>
      <IsPlainTextNodeName>True</IsPlainTextNodeName>
    </Extension>
    <DeviceInfo />
  </Data>
</ReportNode>
<ReportNode type="Step">
<Data>
    <Name>Citilink.Tap</Name>
    <Description />
    <StartTime>2023-01-24 15:17:30</StartTime>
    <Result>Done</Result>
    <Extension>
      <TestObject>
        <Repository>C:\Users\1420\Desktop\Mobile Keagenan Android\Lib_Repo_Excel_Keagenan_Mobile\Repo_Keagenan_Mobile\RP_KeagenanMobile_TiketTransportasi.tsr</Repository>
        <Path>
          <Object>
            <Type>Device</Type>
            <Name><![CDATA[Device]]></Name>
          </Object>
          <Object>
            <Type>App</Type>
            <Name><![CDATA[BNI Agen46]]></Name>
          </Object>
          <Object>
            <Type>MobileObject</Type>
            <Name><![CDATA[Citilink]]></Name>
          </Object>
        </Path>
        <Operation>Tap</Operation>
        <Properties>
          <Property>
            <Name><![CDATA[resourceid]]></Name>
            <Value><![CDATA[]]></Value>
          </Property>
          <Property>
            <Name><![CDATA[nativeclass]]></Name>
            <Value><![CDATA[android.view.View]]></Value>
          </Property>
          <Property>
            <Name><![CDATA[mcindex]]></Name>
            <Value><![CDATA[15]]></Value>
          </Property>
          <Property>
            <Name><![CDATA[class]]></Name>
            <Value><![CDATA[View]]></Value>
          </Property>
          <Property>
            <Name><![CDATA[accessibilityid]]></Name>
            <Value><![CDATA[Citilink]]></Value>
          </Property>
        </Properties>
      </TestObject>
      <IconKey>b887acea2f704ccf9f9d841494ccf91c</IconKey>
      <IsPlainTextNodeName>True</IsPlainTextNodeName>
    </Extension>
    <DeviceInfo />
  </Data>
</ReportNode>
<ReportNode type="Step">
<Data>
    <Name>Kode_Bayar.Tap</Name>
    <Description />
    <StartTime>2023-01-24 15:17:43</StartTime>
    <Result>Done</Result>
    <Extension>
      <TestObject>
        <Repository>C:\Users\1420\Desktop\Mobile Keagenan Android\Lib_Repo_Excel_Keagenan_Mobile\Repo_Keagenan_Mobile\RP_KeagenanMobile_TiketTransportasi.tsr</Repository>
        <Path>
          <Object>
            <Type>Device</Type>
            <Name><![CDATA[Device]]></Name>
          </Object>
          <Object>
            <Type>App</Type>
            <Name><![CDATA[BNI Agen46]]></Name>
          </Object>
          <Object>
            <Type>MobileEdit</Type>
            <Name><![CDATA[Kode_Bayar]]></Name>
          </Object>
        </Path>
        <Operation>Tap</Operation>
        <Properties>
          <Property>
            <Name><![CDATA[resourceid]]></Name>
            <Value><![CDATA[]]></Value>
          </Property>
          <Property>
            <Name><![CDATA[nativeclass]]></Name>
            <Value><![CDATA[android.widget.EditText]]></Value>
          </Property>
          <Property>
            <Name><![CDATA[mcindex]]></Name>
            <Value><![CDATA[0]]></Value>
          </Property>
          <Property>
            <Name><![CDATA[ispassword]]></Name>
            <Value><![CDATA[False]]></Value>
          </Property>
          <Property>
            <Name><![CDATA[class]]></Name>
            <Value><![CDATA[Input]]></Value>
          </Property>
        </Properties>
      </TestObject>
      <IconKey>d793c3a7cf684ab185f02df3005d1263</IconKey>
      <IsPlainTextNodeName>True</IsPlainTextNodeName>
    </Extension>
    <DeviceInfo />
  </Data>
</ReportNode>
<ReportNode type="Step">
<Data>
    <Name>Kode_Bayar.Set</Name>
    <Description>""</Description>
    <StartTime>2023-01-24 15:17:44</StartTime>
    <Result>Done</Result>
    <Extension>
      <TestObject>
        <Repository>C:\Users\1420\Desktop\Mobile Keagenan Android\Lib_Repo_Excel_Keagenan_Mobile\Repo_Keagenan_Mobile\RP_KeagenanMobile_TiketTransportasi.tsr</Repository>
        <Path>
          <Object>
            <Type>Device</Type>
            <Name><![CDATA[Device]]></Name>
          </Object>
          <Object>
            <Type>App</Type>
            <Name><![CDATA[BNI Agen46]]></Name>
          </Object>
          <Object>
            <Type>MobileEdit</Type>
            <Name><![CDATA[Kode_Bayar]]></Name>
          </Object>
        </Path>
        <Operation>Set</Operation>
        <OperationData><![CDATA[""]]></OperationData>
        <Properties>
          <Property>
            <Name><![CDATA[resourceid]]></Name>
            <Value><![CDATA[]]></Value>
          </Property>
          <Property>
            <Name><![CDATA[nativeclass]]></Name>
            <Value><![CDATA[android.widget.EditText]]></Value>
          </Property>
          <Property>
            <Name><![CDATA[mcindex]]></Name>
            <Value><![CDATA[0]]></Value>
          </Property>
          <Property>
            <Name><![CDATA[ispassword]]></Name>
            <Value><![CDATA[False]]></Value>
          </Property>
          <Property>
            <Name><![CDATA[class]]></Name>
            <Value><![CDATA[Input]]></Value>
          </Property>
        </Properties>
      </TestObject>
      <IconKey>d793c3a7cf684ab185f02df3005d1263</IconKey>
      <IsPlainTextNodeName>True</IsPlainTextNodeName>
    </Extension>
    <DeviceInfo />
  </Data>
</ReportNode>
<ReportNode type="Step">
<Data>
    <Name>Lanjut.Tap</Name>
    <Description />
    <StartTime>2023-01-24 15:17:57</StartTime>
    <Result>Done</Result>
    <Extension>
      <TestObject>
        <Repository>C:\Users\1420\Desktop\Mobile Keagenan Android\Lib_Repo_Excel_Keagenan_Mobile\Repo_Keagenan_Mobile\RP_KeagenanMobile_TiketTransportasi.tsr</Repository>
        <Path>
          <Object>
            <Type>Device</Type>
            <Name><![CDATA[Device]]></Name>
          </Object>
          <Object>
            <Type>App</Type>
            <Name><![CDATA[BNI Agen46]]></Name>
          </Object>
          <Object>
            <Type>MobileButton</Type>
            <Name><![CDATA[Lanjut]]></Name>
          </Object>
        </Path>
        <Operation>Tap</Operation>
        <Properties>
          <Property>
            <Name><![CDATA[resourceid]]></Name>
            <Value><![CDATA[]]></Value>
          </Property>
          <Property>
            <Name><![CDATA[nativeclass]]></Name>
            <Value><![CDATA[android.widget.Button]]></Value>
          </Property>
          <Property>
            <Name><![CDATA[mcindex]]></Name>
            <Value><![CDATA[1]]></Value>
          </Property>
          <Property>
            <Name><![CDATA[class]]></Name>
            <Value><![CDATA[Button]]></Value>
          </Property>
          <Property>
            <Name><![CDATA[accessibilityid]]></Name>
            <Value><![CDATA[Lanjut]]></Value>
          </Property>
        </Properties>
      </TestObject>
      <IconKey>8531c7d2c2be471c8b6a3377701d6eea</IconKey>
      <IsPlainTextNodeName>True</IsPlainTextNodeName>
    </Extension>
    <DeviceInfo />
  </Data>
</ReportNode>
<ReportNode type="Step">
<Data>
    <Name>Stop Run</Name>
    <Description>Run stopped by user.</Description>
    <StartTime>2023-01-24 15:18:29</StartTime>
    <Result>Information</Result>
    <Extension>
      <IconKey>35753e3732c04c40801d2285ded6b855</IconKey>
      <IsPlainTextNodeName>True</IsPlainTextNodeName>
    </Extension>
  </Data>
</ReportNode>
<Data>
    <Name>BNI Agen46 [version 2]</Name>
    <Description>&lt;table&gt;&lt;tr&gt;&lt;td style="text-align : left; font-size : 12px; font-weight : 600; "&gt;Package Name:&lt;/td&gt;&lt;td style="text-align : left; font-size : 12px; "&gt;id.co.bni.newagenbni46&lt;/td&gt;&lt;/tr&gt;&lt;tr&gt;&lt;td style="text-align : left; font-size : 12px; font-weight : 600; "&gt;Version:&lt;/td&gt;&lt;td style="text-align : left; font-size : 12px; "&gt;2&lt;/td&gt;&lt;/tr&gt;&lt;/table&gt;</Description>
    <StartTime>2023-01-24 15:16:57</StartTime>
    <Duration>92</Duration>
    <Result>Done</Result>
    <Extension>
      <TestObject>
        <Repository>C:\Users\1420\Desktop\Mobile Keagenan Android\Lib_Repo_Excel_Keagenan_Mobile\Repo_Keagenan_Mobile\RP_Keagenan_Mobile.tsr</Repository>
        <Path>
          <Object>
            <Type>Device</Type>
            <Name><![CDATA[Device]]></Name>
          </Object>
          <Object>
            <Type>App</Type>
            <Name><![CDATA[BNI Agen46]]></Name>
          </Object>
        </Path>
        <Operation> [version 2]</Operation>
        <OperationData><![CDATA[<table><tr><td style="text-align : left; font-size : 12px; font-weight : 600; ">Package Name:</td><td style="text-align : left; font-size : 12px; ">id.co.bni.newagenbni46</td></tr><tr><td style="text-align : left; font-size : 12px; font-weight : 600; ">Version:</td><td style="text-align : left; font-size : 12px; ">2</td></tr></table>]]></OperationData>
        <Properties>
          <Property>
            <Name><![CDATA[instrumented]]></Name>
            <Value><![CDATA[False]]></Value>
          </Property>
          <Property>
            <Name><![CDATA[identifier]]></Name>
            <Value><![CDATA[id.co.bni.newagenbni46]]></Value>
          </Property>
        </Properties>
      </TestObject>
      <IconKey>90d79a21fbca49228f0e96aa0e403768</IconKey>
      <IsPlainTextNodeName>True</IsPlainTextNodeName>
    </Extension>
  </Data>
</ReportNode>
<Data>
    <Name>Device [samsung SM-A525F]</Name>
    <Description>&lt;table&gt;&lt;tr&gt;&lt;td&gt;&lt;span style="text-align : left; font-size : 12px; font-weight : 600; "&gt;ID: &lt;/span&gt;&lt;span style="text-align : left; font-size : 12px; "&gt;RR8R8097ECH&lt;/span&gt;&lt;/td&gt;&lt;/tr&gt;&lt;tr&gt;&lt;td&gt;&lt;span style="text-align : left; font-size : 12px; font-weight : 600; "&gt;Manufacturer: &lt;/span&gt;&lt;span style="text-align : left; font-size : 12px; "&gt;samsung&lt;/span&gt;&lt;/td&gt;&lt;/tr&gt;&lt;tr&gt;&lt;td&gt;&lt;span style="text-align : left; font-size : 12px; font-weight : 600; "&gt;Model: &lt;/span&gt;&lt;span style="text-align : left; font-size : 12px; "&gt;SM-A525F&lt;/span&gt;&lt;/td&gt;&lt;/tr&gt;&lt;tr&gt;&lt;td&gt;&lt;span style="text-align : left; font-size : 12px; font-weight : 600; "&gt;OS Type: &lt;/span&gt;&lt;span style="text-align : left; font-size : 12px; "&gt;ANDROID&lt;/span&gt;&lt;/td&gt;&lt;/tr&gt;&lt;tr&gt;&lt;td&gt;&lt;span style="text-align : left; font-size : 12px; font-weight : 600; "&gt;OS Version: &lt;/span&gt;&lt;span style="text-align : left; font-size : 12px; "&gt;11&lt;/span&gt;&lt;/td&gt;&lt;/tr&gt;&lt;tr&gt;&lt;td&gt;&lt;span style="text-align : left; font-size : 12px; font-weight : 600; "&gt;Source: &lt;/span&gt;&lt;span style="text-align : left; font-size : 12px; "&gt;MC&lt;/span&gt;&lt;/td&gt;&lt;/tr&gt;&lt;/table&gt;</Description>
    <StartTime>2023-01-24 15:16:57</StartTime>
    <Duration>92</Duration>
    <Result>Done</Result>
    <Extension>
      <TestObject>
        <Repository>C:\Users\1420\Desktop\Mobile Keagenan Android\Lib_Repo_Excel_Keagenan_Mobile\Repo_Keagenan_Mobile\RP_Keagenan_Mobile.tsr</Repository>
        <Path>
          <Object>
            <Type>Device</Type>
            <Name><![CDATA[Device]]></Name>
          </Object>
        </Path>
        <Operation> [samsung SM-A525F]</Operation>
        <OperationData><![CDATA[<table><tr><td><span style="text-align : left; font-size : 12px; font-weight : 600; ">ID: </span><span style="text-align : left; font-size : 12px; ">RR8R8097ECH</span></td></tr><tr><td><span style="text-align : left; font-size : 12px; font-weight : 600; ">Manufacturer: </span><span style="text-align : left; font-size : 12px; ">samsung</span></td></tr><tr><td><span style="text-align : left; font-size : 12px; font-weight : 600; ">Model: </span><span style="text-align : left; font-size : 12px; ">SM-A525F</span></td></tr><tr><td><span style="text-align : left; font-size : 12px; font-weight : 600; ">OS Type: </span><span style="text-align : left; font-size : 12px; ">ANDROID</span></td></tr><tr><td><span style="text-align : left; font-size : 12px; font-weight : 600; ">OS Version: </span><span style="text-align : left; font-size : 12px; ">11</span></td></tr><tr><td><span style="text-align : left; font-size : 12px; font-weight : 600; ">Source: </span><span style="text-align : left; font-size : 12px; ">MC</span></td></tr></table>]]></OperationData>
      </TestObject>
      <IconKey>a358e977a2b844ca98c278a2e86e9b6a</IconKey>
      <IsPlainTextNodeName>True</IsPlainTextNodeName>
    </Extension>
  </Data>
</ReportNode>
<Data>
    <Name>SMAG0026 - Tiket Penerbangan</Name>
    <Description />
    <StartTime>2023-01-24 15:16:35</StartTime>
    <Duration>114</Duration>
    <Result>Passed</Result>
    <Extension>
      <IconKey>f56967b71bd24b98a6771e48e0c6b2c0</IconKey>
      <IsPlainTextNodeName>True</IsPlainTextNodeName>
    </Extension>
    <Index>1</Index>
  </Data>
</ReportNode>
<Data>
    <Name>SMAG0026 - Tiket Penerbangan</Name>
    <Description />
    <StartTime>2023-01-24 15:16:35</StartTime>
    <Duration>114</Duration>
    <Result>Passed</Result>
    <InputParameters />
    <Extension>
      <IconKey>2648bfe24e0b445da514e73351fe82b2</IconKey>
      <IsPlainTextNodeName>True</IsPlainTextNodeName>
    </Extension>
  </Data>
</ReportNode>
<Data>
    <Name>Action0</Name>
    <Description />
    <StartTime>2023-01-24 15:16:34</StartTime>
    <Duration>115</Duration>
    <Result>Passed</Result>
    <Extension>
      <IconKey>f56967b71bd24b98a6771e48e0c6b2c0</IconKey>
      <IsPlainTextNodeName>True</IsPlainTextNodeName>
    </Extension>
    <Index>1</Index>
    <TestedApplications />
  </Data>
</ReportNode>
<ReportNode type="Step">
<Data>
    <Name>Stop Run</Name>
    <Description>Run stopped by user.</Description>
    <StartTime>2023-01-24 15:18:29</StartTime>
    <Result>Information</Result>
    <Extension>
      <IconKey>9c8994c55aec437d9f0a7825e34c9e25</IconKey>
      <IsPlainTextNodeName>True</IsPlainTextNodeName>
    </Extension>
  </Data>
</ReportNode>
<Data>
    <Name>SMAG0026_TiketTransportasi_Penerbangan_n_DaftarFavorite</Name>
    <ToolName>Micro Focus UFT One</ToolName>
    <ToolVersion>2021</ToolVersion>
    <ToolVersionStringLiteral>2021</ToolVersionStringLiteral>
    <Description />
    <StartTime>2023-01-24 15:16:31</StartTime>
    <Duration>118</Duration>
    <Result>Passed</Result>
    <InputParameters />
    <Extension>
      <IconKey>b371600ae78043dc8d0f6910e5f1e284</IconKey>
      <IsPlainTextNodeName>True</IsPlainTextNodeName>
    </Extension>
    <Environment>
      <Timezone>+04:00:00</Timezone>
      <Locale>English (Indonesia)</Locale>
      <User>1420</User>
      <CpuInfo>AMD Ryzen 5 5500U with Radeon Graphics         </CpuInfo>
      <NumberOfCores>12</NumberOfCores>
      <TotalMemory>6006</TotalMemory>
      <HostName>OKIKUSMAHESA</HostName>
      <OSInfo>Windows 11 22H2 (x64)</OSInfo>
    </Environment>
    <TestedApplications />
    <Links>
      <Link type="DataTable" reference="Default.xlsx" displayname="Default Data Table" />
    </Links>
  </Data>
</ReportNode>
<GeneralInfo>
    <ResultName>Res2</ResultName>
    <RunStartTime>2023-01-24 15:16:31</RunStartTime>
    <Timezone>+04:00:00</Timezone>
    <OrchestrationToolName>Micro Focus UFT One</OrchestrationToolName>
    <OrchestrationToolVersion>2021</OrchestrationToolVersion>
    <OrchestrationToolVersionStringLiteral>2021</OrchestrationToolVersionStringLiteral>
  </GeneralInfo>
</Results>