<?xml version="1.0"?>
<Results version="1.0">
<ReportNode type="testrun">
<ReportNode type="Iteration">
<ReportNode type="Action">
<ReportNode type="Iteration">
<ReportNode type="Step">
<Data>
    <Name>LoadFunctionLibrary</Name>
    <Description>LoadFunctionLibrary function passed</Description>
    <StartTime>2022-11-04 16:02:34</StartTime>
    <Result>Passed</Result>
    <Extension>
      <IconKey>2fd74639ae86410c8244348775bfae40</IconKey>
      <IsPlainTextNodeName>True</IsPlainTextNodeName>
    </Extension>
    <DeviceInfo />
  </Data>
</ReportNode>
<ReportNode type="Step">
<Data>
    <Name>LoadFunctionLibrary</Name>
    <Description>LoadFunctionLibrary function passed</Description>
    <StartTime>2022-11-04 16:02:34</StartTime>
    <Result>Passed</Result>
    <Extension>
      <IconKey>2fd74639ae86410c8244348775bfae40</IconKey>
      <IsPlainTextNodeName>True</IsPlainTextNodeName>
    </Extension>
    <DeviceInfo />
  </Data>
</ReportNode>
<ReportNode type="Step">
<Data>
    <Name>LoadFunctionLibrary</Name>
    <Description>LoadFunctionLibrary function passed</Description>
    <StartTime>2022-11-04 16:02:34</StartTime>
    <Result>Passed</Result>
    <Extension>
      <IconKey>2fd74639ae86410c8244348775bfae40</IconKey>
      <IsPlainTextNodeName>True</IsPlainTextNodeName>
    </Extension>
    <DeviceInfo />
  </Data>
</ReportNode>
<ReportNode type="Step">
<Data>
    <Name>LoadFunctionLibrary</Name>
    <Description>LoadFunctionLibrary function passed</Description>
    <StartTime>2022-11-04 16:02:35</StartTime>
    <Result>Passed</Result>
    <Extension>
      <IconKey>2fd74639ae86410c8244348775bfae40</IconKey>
      <IsPlainTextNodeName>True</IsPlainTextNodeName>
    </Extension>
    <DeviceInfo />
  </Data>
</ReportNode>
<ReportNode type="Step">
<Data>
    <Name>LoadFunctionLibrary</Name>
    <Description>LoadFunctionLibrary function passed</Description>
    <StartTime>2022-11-04 16:02:35</StartTime>
    <Result>Passed</Result>
    <Extension>
      <IconKey>2fd74639ae86410c8244348775bfae40</IconKey>
      <IsPlainTextNodeName>True</IsPlainTextNodeName>
    </Extension>
    <DeviceInfo />
  </Data>
</ReportNode>
<ReportNode type="Step">
<Data>
    <Name>Stop action iteration replay</Name>
    <Description>Run stopped by user.</Description>
    <StartTime>2022-11-04 16:02:35</StartTime>
    <Result>Information</Result>
    <Extension>
      <IconKey>289fcd4a1b6a42979b3232127107caf7</IconKey>
      <IsPlainTextNodeName>True</IsPlainTextNodeName>
    </Extension>
  </Data>
</ReportNode>
<Data>
    <Name>SMAG-0009 - Setor Tunai</Name>
    <Description />
    <StartTime>2022-11-04 16:02:34</StartTime>
    <Duration>1</Duration>
    <Result>Passed</Result>
    <Extension>
      <IconKey>d07542b6c8264468b19e7e9afe7588ef</IconKey>
      <IsPlainTextNodeName>True</IsPlainTextNodeName>
    </Extension>
    <Index>1</Index>
    <TestedApplications />
  </Data>
</ReportNode>
<ReportNode type="Iteration">
<ReportNode type="Step">
<Data>
    <Name>LoadFunctionLibrary</Name>
    <Description>LoadFunctionLibrary function passed</Description>
    <StartTime>2022-11-04 16:02:35</StartTime>
    <Result>Passed</Result>
    <Extension>
      <IconKey>2fd74639ae86410c8244348775bfae40</IconKey>
      <IsPlainTextNodeName>True</IsPlainTextNodeName>
    </Extension>
    <DeviceInfo />
  </Data>
</ReportNode>
<ReportNode type="Step">
<Data>
    <Name>LoadFunctionLibrary</Name>
    <Description>LoadFunctionLibrary function passed</Description>
    <StartTime>2022-11-04 16:02:35</StartTime>
    <Result>Passed</Result>
    <Extension>
      <IconKey>2fd74639ae86410c8244348775bfae40</IconKey>
      <IsPlainTextNodeName>True</IsPlainTextNodeName>
    </Extension>
    <DeviceInfo />
  </Data>
</ReportNode>
<ReportNode type="Step">
<Data>
    <Name>LoadFunctionLibrary</Name>
    <Description>LoadFunctionLibrary function passed</Description>
    <StartTime>2022-11-04 16:02:35</StartTime>
    <Result>Passed</Result>
    <Extension>
      <IconKey>2fd74639ae86410c8244348775bfae40</IconKey>
      <IsPlainTextNodeName>True</IsPlainTextNodeName>
    </Extension>
    <DeviceInfo />
  </Data>
</ReportNode>
<ReportNode type="Step">
<Data>
    <Name>LoadFunctionLibrary</Name>
    <Description>LoadFunctionLibrary function passed</Description>
    <StartTime>2022-11-04 16:02:35</StartTime>
    <Result>Passed</Result>
    <Extension>
      <IconKey>2fd74639ae86410c8244348775bfae40</IconKey>
      <IsPlainTextNodeName>True</IsPlainTextNodeName>
    </Extension>
    <DeviceInfo />
  </Data>
</ReportNode>
<ReportNode type="Step">
<Data>
    <Name>LoadFunctionLibrary</Name>
    <Description>LoadFunctionLibrary function passed</Description>
    <StartTime>2022-11-04 16:02:35</StartTime>
    <Result>Passed</Result>
    <Extension>
      <IconKey>2fd74639ae86410c8244348775bfae40</IconKey>
      <IsPlainTextNodeName>True</IsPlainTextNodeName>
    </Extension>
    <DeviceInfo />
  </Data>
</ReportNode>
<ReportNode type="Step">
<Data>
    <Name>Stop action iteration replay</Name>
    <Description>Run stopped by user.</Description>
    <StartTime>2022-11-04 16:02:35</StartTime>
    <Result>Information</Result>
    <Extension>
      <IconKey>289fcd4a1b6a42979b3232127107caf7</IconKey>
      <IsPlainTextNodeName>True</IsPlainTextNodeName>
    </Extension>
  </Data>
</ReportNode>
<Data>
    <Name>SMAG-0009 - Setor Tunai</Name>
    <Description />
    <StartTime>2022-11-04 16:02:35</StartTime>
    <Duration>0</Duration>
    <Result>Passed</Result>
    <Extension>
      <IconKey>d07542b6c8264468b19e7e9afe7588ef</IconKey>
      <IsPlainTextNodeName>True</IsPlainTextNodeName>
    </Extension>
    <Index>2</Index>
    <TestedApplications />
  </Data>
</ReportNode>
<ReportNode type="Iteration">
<ReportNode type="Step">
<Data>
    <Name>LoadFunctionLibrary</Name>
    <Description>LoadFunctionLibrary function passed</Description>
    <StartTime>2022-11-04 16:02:35</StartTime>
    <Result>Passed</Result>
    <Extension>
      <IconKey>2fd74639ae86410c8244348775bfae40</IconKey>
      <IsPlainTextNodeName>True</IsPlainTextNodeName>
    </Extension>
    <DeviceInfo />
  </Data>
</ReportNode>
<ReportNode type="Step">
<Data>
    <Name>LoadFunctionLibrary</Name>
    <Description>LoadFunctionLibrary function passed</Description>
    <StartTime>2022-11-04 16:02:35</StartTime>
    <Result>Passed</Result>
    <Extension>
      <IconKey>2fd74639ae86410c8244348775bfae40</IconKey>
      <IsPlainTextNodeName>True</IsPlainTextNodeName>
    </Extension>
    <DeviceInfo />
  </Data>
</ReportNode>
<ReportNode type="Step">
<Data>
    <Name>LoadFunctionLibrary</Name>
    <Description>LoadFunctionLibrary function passed</Description>
    <StartTime>2022-11-04 16:02:35</StartTime>
    <Result>Passed</Result>
    <Extension>
      <IconKey>2fd74639ae86410c8244348775bfae40</IconKey>
      <IsPlainTextNodeName>True</IsPlainTextNodeName>
    </Extension>
    <DeviceInfo />
  </Data>
</ReportNode>
<ReportNode type="Step">
<Data>
    <Name>LoadFunctionLibrary</Name>
    <Description>LoadFunctionLibrary function passed</Description>
    <StartTime>2022-11-04 16:02:35</StartTime>
    <Result>Passed</Result>
    <Extension>
      <IconKey>2fd74639ae86410c8244348775bfae40</IconKey>
      <IsPlainTextNodeName>True</IsPlainTextNodeName>
    </Extension>
    <DeviceInfo />
  </Data>
</ReportNode>
<ReportNode type="Step">
<Data>
    <Name>LoadFunctionLibrary</Name>
    <Description>LoadFunctionLibrary function passed</Description>
    <StartTime>2022-11-04 16:02:35</StartTime>
    <Result>Passed</Result>
    <Extension>
      <IconKey>2fd74639ae86410c8244348775bfae40</IconKey>
      <IsPlainTextNodeName>True</IsPlainTextNodeName>
    </Extension>
    <DeviceInfo />
  </Data>
</ReportNode>
<ReportNode type="Step">
<Data>
    <Name>Stop action iteration replay</Name>
    <Description>Run stopped by user.</Description>
    <StartTime>2022-11-04 16:02:36</StartTime>
    <Result>Information</Result>
    <Extension>
      <IconKey>289fcd4a1b6a42979b3232127107caf7</IconKey>
      <IsPlainTextNodeName>True</IsPlainTextNodeName>
    </Extension>
  </Data>
</ReportNode>
<Data>
    <Name>SMAG-0009 - Setor Tunai</Name>
    <Description />
    <StartTime>2022-11-04 16:02:35</StartTime>
    <Duration>1</Duration>
    <Result>Passed</Result>
    <Extension>
      <IconKey>d07542b6c8264468b19e7e9afe7588ef</IconKey>
      <IsPlainTextNodeName>True</IsPlainTextNodeName>
    </Extension>
    <Index>3</Index>
    <TestedApplications />
  </Data>
</ReportNode>
<ReportNode type="Iteration">
<ReportNode type="Step">
<Data>
    <Name>LoadFunctionLibrary</Name>
    <Description>LoadFunctionLibrary function passed</Description>
    <StartTime>2022-11-04 16:02:36</StartTime>
    <Result>Passed</Result>
    <Extension>
      <IconKey>2fd74639ae86410c8244348775bfae40</IconKey>
      <IsPlainTextNodeName>True</IsPlainTextNodeName>
    </Extension>
    <DeviceInfo />
  </Data>
</ReportNode>
<ReportNode type="Step">
<Data>
    <Name>LoadFunctionLibrary</Name>
    <Description>LoadFunctionLibrary function passed</Description>
    <StartTime>2022-11-04 16:02:36</StartTime>
    <Result>Passed</Result>
    <Extension>
      <IconKey>2fd74639ae86410c8244348775bfae40</IconKey>
      <IsPlainTextNodeName>True</IsPlainTextNodeName>
    </Extension>
    <DeviceInfo />
  </Data>
</ReportNode>
<ReportNode type="Step">
<Data>
    <Name>LoadFunctionLibrary</Name>
    <Description>LoadFunctionLibrary function passed</Description>
    <StartTime>2022-11-04 16:02:36</StartTime>
    <Result>Passed</Result>
    <Extension>
      <IconKey>2fd74639ae86410c8244348775bfae40</IconKey>
      <IsPlainTextNodeName>True</IsPlainTextNodeName>
    </Extension>
    <DeviceInfo />
  </Data>
</ReportNode>
<ReportNode type="Step">
<Data>
    <Name>LoadFunctionLibrary</Name>
    <Description>LoadFunctionLibrary function passed</Description>
    <StartTime>2022-11-04 16:02:36</StartTime>
    <Result>Passed</Result>
    <Extension>
      <IconKey>2fd74639ae86410c8244348775bfae40</IconKey>
      <IsPlainTextNodeName>True</IsPlainTextNodeName>
    </Extension>
    <DeviceInfo />
  </Data>
</ReportNode>
<ReportNode type="Step">
<Data>
    <Name>LoadFunctionLibrary</Name>
    <Description>LoadFunctionLibrary function passed</Description>
    <StartTime>2022-11-04 16:02:36</StartTime>
    <Result>Passed</Result>
    <Extension>
      <IconKey>2fd74639ae86410c8244348775bfae40</IconKey>
      <IsPlainTextNodeName>True</IsPlainTextNodeName>
    </Extension>
    <DeviceInfo />
  </Data>
</ReportNode>
<ReportNode type="Step">
<Data>
    <Name>Stop action iteration replay</Name>
    <Description>Run stopped by user.</Description>
    <StartTime>2022-11-04 16:02:36</StartTime>
    <Result>Information</Result>
    <Extension>
      <IconKey>289fcd4a1b6a42979b3232127107caf7</IconKey>
      <IsPlainTextNodeName>True</IsPlainTextNodeName>
    </Extension>
  </Data>
</ReportNode>
<Data>
    <Name>SMAG-0009 - Setor Tunai</Name>
    <Description />
    <StartTime>2022-11-04 16:02:36</StartTime>
    <Duration>0</Duration>
    <Result>Passed</Result>
    <Extension>
      <IconKey>d07542b6c8264468b19e7e9afe7588ef</IconKey>
      <IsPlainTextNodeName>True</IsPlainTextNodeName>
    </Extension>
    <Index>4</Index>
    <TestedApplications />
  </Data>
</ReportNode>
<ReportNode type="Iteration">
<ReportNode type="Step">
<Data>
    <Name>LoadFunctionLibrary</Name>
    <Description>LoadFunctionLibrary function passed</Description>
    <StartTime>2022-11-04 16:02:36</StartTime>
    <Result>Passed</Result>
    <Extension>
      <IconKey>2fd74639ae86410c8244348775bfae40</IconKey>
      <IsPlainTextNodeName>True</IsPlainTextNodeName>
    </Extension>
    <DeviceInfo />
  </Data>
</ReportNode>
<ReportNode type="Step">
<Data>
    <Name>LoadFunctionLibrary</Name>
    <Description>LoadFunctionLibrary function passed</Description>
    <StartTime>2022-11-04 16:02:36</StartTime>
    <Result>Passed</Result>
    <Extension>
      <IconKey>2fd74639ae86410c8244348775bfae40</IconKey>
      <IsPlainTextNodeName>True</IsPlainTextNodeName>
    </Extension>
    <DeviceInfo />
  </Data>
</ReportNode>
<ReportNode type="Step">
<Data>
    <Name>LoadFunctionLibrary</Name>
    <Description>LoadFunctionLibrary function passed</Description>
    <StartTime>2022-11-04 16:02:36</StartTime>
    <Result>Passed</Result>
    <Extension>
      <IconKey>2fd74639ae86410c8244348775bfae40</IconKey>
      <IsPlainTextNodeName>True</IsPlainTextNodeName>
    </Extension>
    <DeviceInfo />
  </Data>
</ReportNode>
<ReportNode type="Step">
<Data>
    <Name>LoadFunctionLibrary</Name>
    <Description>LoadFunctionLibrary function passed</Description>
    <StartTime>2022-11-04 16:02:36</StartTime>
    <Result>Passed</Result>
    <Extension>
      <IconKey>2fd74639ae86410c8244348775bfae40</IconKey>
      <IsPlainTextNodeName>True</IsPlainTextNodeName>
    </Extension>
    <DeviceInfo />
  </Data>
</ReportNode>
<ReportNode type="Step">
